{
  "package": "@fortawesome/free-brands-svg-icons",
  "downloads": {
    "6.5.1": 181662,
    "5.15.2": 79055,
    "5.13.0": 16433,
    "5.8.0": 20,
    "5.14.0": 17038,
    "5.1.0-4": 3,
    "6.1.2": 7762,
    "6.1.0": 1607,
    "6.2.0": 24733,
    "5.6.0": 8,
    "5.12.1": 6452,
    "5.13.1": 26892,
    "5.10.0-6": 1,
    "5.10.0": 420,
    "6.4.0": 34636,
    "5.11.0": 13,
    "5.6.1": 516,
    "5.1.0-8": 16,
    "6.4.2": 69776,
    "5.10.0-12": 1,
    "5.9.0": 1502,
    "5.7.1": 1187,
    "5.10.0-13": 1,
    "6.3.0": 46109,
    "5.10.2": 1840,
    "5.15.1": 32895,
    "5.8.1": 1225,
    "5.8.2": 1936,
    "5.10.0-8": 1,
    "5.4.2": 336,
    "5.1.0": 155,
    "5.6.3": 523,
    "5.1.0-10": 4,
    "5.3.1": 629,
    "5.15.4": 345639,
    "5.10.0-11": 1,
    "6.0.0-beta2": 215,
    "5.11.1": 1266,
    "5.1.0-5": 3,
    "5.4.0": 35,
    "6.5.0": 1503,
    "5.10.1": 1021,
    "5.1.0-6": 3,
    "5.2.0": 128,
    "5.3.0": 9,
    "5.1.0-7": 9,
    "6.2.1": 33449,
    "5.1.0-9": 7,
    "5.4.1": 85,
    "5.7.2": 5004,
    "5.5.0": 294,
    "5.11.2": 12287,
    "5.6.2": 1,
    "5.12.0": 4348,
    "5.7.0": 92,
    "5.12.0-1": 1,
    "5.1.1": 13,
    "5.10.0-3": 1,
    "5.15.3": 44544,
    "5.10.0-1": 2,
    "6.0.0-beta3": 384,
    "5.1.0-11": 53,
    "5.12.0-2": 21,
    "5.15.0": 1651,
    "6.0.0": 20493,
    "6.1.1": 25757
  },
  "end": "2024-03-04T04:45:39.865Z",
  "start": "2024-02-26T04:45:39.865Z"
}