{
  "package": "typeorm",
  "downloads": {
    "0.3.0-rc.34": 1,
    "0.3.5": 1700,
    "0.2.0-alpha.6": 3,
    "0.0.2-alpha.13": 2,
    "0.3.0-alpha.5": 2,
    "0.2.0-alpha.46": 2,
    "0.3.18-dev.c6f608d": 5,
    "0.2.38": 41116,
    "0.0.2-alpha.30": 2,
    "0.3.0-alpha.9": 2,
    "0.3.0-rc.5": 13,
    "0.2.46-dev.486f8c5": 35,
    "0.3.12-dev.b8704f8": 4,
    "0.0.2-alpha.51": 2,
    "0.0.8-alpha.5": 2,
    "0.3.20-dev.15de46f": 4,
    "0.3.4-dev.ceee439": 2,
    "0.3.0-rc.11": 2,
    "0.3.17-dev.b1a3a39": 4,
    "0.3.0-alpha.7": 2,
    "0.2.42-dev.3284808": 3,
    "0.2.41-dev.8a5e671": 2,
    "0.2.45-dev.6523526": 43,
    "0.2.9": 1478,
    "0.1.0-alpha.9": 2,
    "0.3.15-dev.f6a3ce7": 1,
    "0.3.2-dev.97699e8": 1,
    "0.2.42-dev.54cf660": 3,
    "0.2.40-dev.0cc8fbb": 2,
    "0.2.37-dev.fe78bee": 2,
    "0.2.40-dev.41ee95c": 2,
    "0.2.42-dev.a0f09de": 2,
    "0.3.16": 52822,
    "0.1.0-alpha.3": 2,
    "0.2.44-dev.136015b": 3,
    "0.2.24": 20554,
    "0.0.7-alpha.2": 2,
    "0.3.0-alpha.4": 3,
    "0.2.43-dev.6ab9b3a": 3,
    "0.2.38-dev.a868078": 2,
    "0.0.3-alpha.5": 2,
    "0.0.1": 7,
    "0.0.5-alpha.4": 2,
    "0.0.2-alpha.54": 2,
    "0.3.20-dev.dd8c0fd": 4,
    "0.3.8-dev.340ab67": 1,
    "0.2.42-dev.26815c6": 4,
    "0.1.11": 36,
    "0.2.37-dev.f0e40f6": 4,
    "0.1.0-alpha.38": 2,
    "0.1.0-alpha.35": 6,
    "0.0.7-alpha.16": 2,
    "0.3.2": 119,
    "0.1.7": 17,
    "0.1.6": 59,
    "0.0.5-alpha.13": 2,
    "0.3.18-dev.65858f3": 5,
    "0.1.21": 262,
    "0.3.3": 161,
    "0.3.0-rc.36": 64,
    "0.1.2": 18,
    "0.0.2-alpha.64": 2,
    "0.2.44-dev.2d3374b": 2,
    "0.0.7-alpha.8": 2,
    "0.3.19-dev.633c4e3": 4,
    "0.2.0-alpha.16": 2,
    "0.0.3-alpha.8": 2,
    "0.2.20": 4870,
    "0.3.12-dev.54ca9dd": 2,
    "0.3.8-dev.e49d0c8": 1,
    "0.3.16-dev.b064049": 4,
    "0.0.2-alpha.15": 2,
    "0.2.1": 10,
    "0.1.5": 4,
    "0.0.7-alpha.9": 2,
    "0.2.43-dev.60a5b84": 3,
    "0.3.18-dev.2dc9624": 4,
    "0.2.37-dev.69fabaf": 2,
    "0.2.0-alpha.15": 4,
    "0.0.2-alpha.19": 2,
    "0.2.37-dev.37c40a6": 3,
    "0.3.12-dev.4df969e": 3,
    "0.3.4-dev.54c7db4": 1,
    "0.3.0-rc.40": 6,
    "0.0.3-alpha.9": 2,
    "0.0.2-alpha.57": 2,
    "0.2.0-alpha.9": 2,
    "0.3.0-alpha.20": 3,
    "0.2.42-dev.ece0da0": 6,
    "0.2.38-dev.22676a0": 2,
    "0.3.11-dev.b5ff79f": 2,
    "0.3.12-dev.67973b4": 2,
    "0.3.18-dev.a939654": 7,
    "0.2.0-alpha.40": 2,
    "0.3.20-dev.8f371f2": 4,
    "0.2.0-alpha.18": 3,
    "0.3.0-rc.16": 3,
    "0.0.7-alpha.25": 2,
    "0.2.39-dev.25271d7": 2,
    "0.2.37-dev.fbbac93": 2,
    "0.3.10-dev.52e5f7c": 1,
    "0.2.33": 2151,
    "0.2.42-dev.8f2ae71": 3,
    "0.3.13": 1330,
    "0.3.8-dev.5e5abbd": 3,
    "0.3.8-dev.3a533a4": 2,
    "0.3.0-alpha.19": 3,
    "0.3.16-dev.06c1e98": 5,
    "0.3.0-rc.12": 2,
    "0.2.39-dev.ef33cf4": 3,
    "0.3.6-dev.78df84c": 1,
    "0.0.7-alpha.22": 2,
    "0.0.3-alpha.7": 2,
    "0.3.0-rc.10": 3,
    "0.3.18-dev.a909d5b": 5,
    "0.0.6": 54,
    "0.0.2-alpha": 2,
    "0.3.4-dev.494008": 2,
    "0.3.5-dev.baa2f44": 4,
    "0.3.5-dev.2205a1a": 1,
    "0.2.42-dev.8898a71": 3,
    "0.3.0-alpha.3": 2,
    "0.0.2-alpha.67": 2,
    "0.0.3-alpha.1": 2,
    "0.0.2-alpha.70": 3,
    "0.2.42-dev.600bd4e": 4,
    "0.1.10": 14,
    "0.2.39-dev.b6c828c": 2,
    "0.3.6-dev.189592c": 1,
    "0.3.4-dev.d2cfd22": 2,
    "0.3.14-dev.daf1b47": 1,
    "0.3.14-dev.0194f17": 1,
    "0.0.8-alpha.3": 2,
    "0.3.0-rc.9": 5,
    "0.0.2-alpha.11": 2,
    "0.2.39-dev.f79ae58": 3,
    "0.2.44-dev.2c2fb29": 4,
    "0.2.39-dev.503d1dc": 2,
    "0.3.8-dev.68e8f22": 1,
    "0.3.5-dev.3730fd0": 2,
    "0.1.0-alpha.2": 2,
    "0.0.3-alpha.15": 2,
    "0.1.17": 51,
    "0.3.6-dev.e24cced": 2,
    "0.3.15-dev.f1c5662": 4,
    "0.2.42-dev.1cfd7b9": 3,
    "0.2.14": 255,
    "0.2.41": 128269,
    "0.2.42-dev.f7c1f7d": 3,
    "0.3.0-alpha.12": 14,
    "0.3.11": 140818,
    "0.3.18-dev.0f11739": 7,
    "0.2.39-dev.28c183e": 3,
    "0.2.0-alpha.12": 3,
    "0.3.1-dev.941b584": 2,
    "0.2.39-dev.8615733": 3,
    "0.3.16-dev.9460296": 5,
    "0.1.0-alpha.44": 2,
    "0.3.0-alpha.23": 243,
    "0.0.2-alpha.56": 3,
    "0.0.2-alpha.22": 2,
    "0.2.39-dev.4638dea": 3,
    "0.2.42-dev.cbb61eb": 4,
    "0.1.0-alpha.12": 2,
    "0.3.11-dev.d71e9c4": 2,
    "0.0.8-alpha.1": 2,
    "0.1.16": 39,
    "0.3.21-dev.83567f5": 1269,
    "0.3.12-dev.ef64bfc": 5,
    "0.3.6-dev.506133e": 1,
    "0.3.11-dev.1cb738a": 1,
    "0.3.0-rc.14": 2,
    "0.2.0-alpha.41": 2,
    "0.0.3-alpha.19": 2,
    "0.0.8-alpha.6": 2,
    "0.0.3-alpha.11": 2,
    "0.2.42-dev.93bf96e": 2,
    "0.3.0-rc.35": 7,
    "0.2.41-dev.91080be": 3,
    "0.2.8-rc.1": 2,
    "0.2.0-alpha.27": 2,
    "0.0.5-alpha.2": 2,
    "0.2.0-alpha.17": 2,
    "0.3.6-dev.d0ed02d": 2,
    "0.3.8-dev.03317a3": 1,
    "0.3.0-rc.37": 1,
    "0.2.0": 159,
    "0.0.2-alpha.27": 2,
    "0.3.8-dev.c4f4650": 2,
    "0.3.0-alpha.17": 3,
    "0.2.37": 40146,
    "0.2.30": 37289,
    "0.3.21-dev.28a8383": 4,
    "0.3.20-dev.c22e30f": 5,
    "0.3.20-dev.d0b7670": 5,
    "0.0.2-alpha.16": 2,
    "0.0.5-alpha.9": 2,
    "0.3.17-dev.abb9079": 5,
    "0.3.0-alpha.2": 2,
    "0.3.13-dev.f7b210b": 1,
    "0.0.8-alpha.2": 2,
    "0.0.2-alpha.33": 2,
    "0.2.32": 53066,
    "0.0.2-alpha.47": 2,
    "0.3.0-alpha.16": 2,
    "0.0.2-alpha.35": 2,
    "0.3.6-dev.2d8afbe": 2,
    "0.0.2-alpha.26": 2,
    "0.3.18-dev.e67d704": 7,
    "0.3.10-dev.749809a": 1,
    "0.2.15": 1193,
    "0.2.12-rc.2": 401,
    "0.2.38-dev.e9366b3": 4,
    "0.2.42-dev.ce69228": 3,
    "0.2.45-dev.96ac8f7": 2,
    "0.3.10-dev.cc63961": 1,
    "0.1.0-alpha.18": 2,
    "0.0.7-alpha.6": 2,
    "0.2.25": 83859,
    "0.3.2-dev.b53a481": 2,
    "0.2.37-dev.36398db": 2,
    "0.0.3": 4,
    "0.0.2-alpha.37": 2,
    "0.2.0-alpha.32": 2,
    "0.3.6-dev.9f8429f": 1,
    "0.2.41-dev.29cb891": 3,
    "0.3.0-alpha.14": 2,
    "0.1.0-alpha.42": 3,
    "0.2.44-dev.1f54c70": 3,
    "0.1.0-alpha.26": 4,
    "0.2.21": 3270,
    "0.3.18-dev.8d0e7f9": 4,
    "0.2.42-dev.b93416d": 2,
    "0.3.18-dev.b6b46fb": 4,
    "0.3.8-dev.8dcd61e": 3,
    "0.1.0-alpha.36": 2,
    "0.3.11-dev.4a36d0e": 2,
    "0.2.39-dev.b678807": 2,
    "0.3.0-alpha.6": 7,
    "0.0.6-alpha.1": 2,
    "0.0.2-alpha.17": 3,
    "0.2.0-alpha.11": 2,
    "0.3.12-dev.adce698": 3,
    "0.2.10-rc.2": 4,
    "0.3.0-alpha.18": 2,
    "0.3.0-rc.29": 1,
    "0.3.11-dev.97fae63": 2,
    "0.2.45": 269424,
    "0.1.19": 64,
    "0.3.18-dev.15bc887": 3,
    "0.3.10-dev.773a4fe": 2,
    "0.3.5-dev.002274c": 3,
    "0.2.37-dev.f7eb46d": 3,
    "0.0.2-alpha.46": 2,
    "0.0.7-alpha.3": 2,
    "0.1.0-alpha.22": 2,
    "0.0.2-alpha.61": 2,
    "0.3.0-alpha.22": 7,
    "0.1.0": 27,
    "0.2.23": 111,
    "0.3.5-dev.6774605": 2,
    "0.0.2-alpha.44": 2,
    "0.2.0-alpha.1": 3,
    "0.0.7-alpha.11": 2,
    "0.2.7": 1436,
    "0.3.12-dev.1a9b9fb": 3,
    "0.3.6-dev.62518ae": 2,
    "0.3.10-dev.a1960e1": 2,
    "0.3.6-dev.0418ebc": 1,
    "0.0.2-alpha.28": 2,
    "0.2.37-dev.ca26297": 2,
    "0.0.2-alpha.59": 2,
    "0.2.0-alpha.42": 3,
    "0.3.14": 17185,
    "0.3.18-dev.a4900ae": 4,
    "0.2.42-dev.0626ed1": 3,
    "0.3.11-dev.658604d": 1,
    "0.2.41-dev.15ad5ac": 1,
    "0.2.38-dev.d4111ce": 2,
    "0.1.0-alpha.40": 2,
    "0.0.5-alpha.6": 2,
    "0.3.8-dev.d285fd0": 2,
    "0.2.22-rc.1": 2,
    "0.3.18-dev.f6bb671": 5,
    "0.1.8": 7,
    "0.3.2-dev.c8fb1bb": 2,
    "0.0.2-alpha.60": 2,
    "0.3.18-dev.c8ee5b1": 4,
    "0.2.39-dev.1197f88": 3,
    "0.3.5-dev.ec6c119": 2,
    "0.3.18-dev.befe4f9": 4,
    "0.2.42-dev.4a7f242": 4,
    "0.3.10-dev.de15df1": 1,
    "0.3.0-rc.4": 3,
    "0.2.12": 446,
    "0.3.6-dev.ef025bd": 2,
    "0.1.18": 16,
    "0.3.12-dev.8251812": 1,
    "0.2.41-dev.c59ef29": 1,
    "0.3.11-dev.efb4168": 3,
    "0.2.46-dev.5608956": 1,
    "0.3.5-dev.e58c796": 3,
    "0.2.0-alpha.36": 2,
    "0.3.10-dev.f24b262": 2,
    "0.3.1": 241,
    "0.1.0-alpha.43": 37,
    "0.3.10": 68829,
    "0.2.41-dev.d494fcc": 2,
    "0.2.37-dev.fbd1ef7": 2,
    "0.2.38-dev.749511d": 17,
    "0.2.43-dev.7dbe956": 2,
    "0.3.0-rc.31": 4,
    "0.1.0-alpha.21": 2,
    "0.3.16-dev.68aa573": 6,
    "0.0.5-alpha.11": 2,
    "0.3.11-dev.7fbc3ad": 2,
    "0.3.16-dev.d8a2e37": 3,
    "0.3.0-alpha.15": 2,
    "0.3.6-dev.ea176b2": 2,
    "0.3.11-dev.f07fb2c": 3,
    "0.0.6-alpha.2": 2,
    "0.2.0-alpha.4": 3,
    "0.2.41-dev.c895680": 1,
    "0.2.42-dev.2834729": 1,
    "0.2.0-alpha.31": 2,
    "0.3.4": 437,
    "0.0.2-alpha.43": 2,
    "0.1.15": 36,
    "0.3.11-dev.7386318": 2,
    "0.3.11-dev.5253c8f": 3,
    "0.2.40-dev.e80f97d": 2,
    "0.0.2-alpha.20": 2,
    "0.3.16-dev.e0165e7": 32,
    "0.0.3-alpha.20": 2,
    "0.0.9-alpha.2": 2,
    "0.3.18-dev.022d2b5": 6,
    "0.0.7-alpha.18": 2,
    "0.1.0-alpha.49": 2,
    "0.2.39-dev.1649882": 3,
    "0.3.5-dev.69c33a2": 2,
    "0.3.18-dev.3cda7ec": 6,
    "0.0.2-alpha.53": 2,
    "0.1.0-alpha.39": 3,
    "0.3.16-dev.2a2bb4b": 4,
    "0.3.0-rc.2": 24,
    "0.3.0": 4687,
    "0.1.0-alpha.34": 2,
    "0.3.5-dev.9ac8e9e": 2,
    "0.2.42-dev.f3e2b0e": 2,
    "0.3.6-dev.b84cb9b": 2,
    "0.3.8-dev.64674e6": 2,
    "0.3.12-dev.ae91c05": 3,
    "0.2.42-dev.26581d0": 4,
    "0.3.18": 1039,
    "0.1.0-alpha.20": 2,
    "0.2.0-alpha.45": 2,
    "0.2.28": 17695,
    "0.0.10": 60,
    "0.2.39-dev.0bc194c": 2,
    "0.2.39-dev.6558295": 3,
    "0.1.0-alpha.33": 7,
    "0.3.0-rc.33": 2,
    "0.2.42": 5322,
    "0.0.5-alpha.3": 2,
    "0.2.4": 16,
    "0.3.20-dev.4624930": 4,
    "0.2.11": 249,
    "0.3.6-dev.c814b07": 2,
    "0.3.11-dev.cdabaa3": 2,
    "0.3.12-dev.7df2ccf": 4,
    "0.3.12-dev.ca315f0": 4,
    "0.3.11-dev.19536ed": 1,
    "0.3.6-dev.22570f5": 1,
    "0.0.7-alpha.1": 2,
    "0.3.18-dev.f6b87e3": 8,
    "0.3.8-dev.de8aaac": 2,
    "0.3.0-rc.17": 4,
    "0.3.0-rc.21": 534,
    "0.1.0-alpha.16": 3,
    "0.3.8-dev.0b54222": 1,
    "0.3.11-dev.8a837f9": 2,
    "0.2.37-dev.a5e4ce7": 2,
    "0.2.42-dev.9e844d9": 3,
    "0.2.42-dev.d0f32b3": 3,
    "0.0.2-alpha.18": 2,
    "0.2.27": 508,
    "0.0.5-alpha.10": 2,
    "0.0.7": 5,
    "0.0.2-alpha.34": 3,
    "0.0.2-alpha.31": 2,
    "0.3.3-dev.7cc1848": 1,
    "0.3.12-dev.b97633b": 3,
    "0.2.42-dev.93383bd": 3,
    "0.3.17": 538350,
    "0.0.2-alpha.36": 3,
    "0.1.0-alpha.30": 2,
    "0.1.0-alpha.29": 2,
    "0.3.17-dev.d4607a8": 3,
    "0.2.40": 10155,
    "0.2.39-dev.d7d19e9": 2,
    "0.1.0-alpha.24": 2,
    "0.0.2-alpha.3": 2,
    "0.0.11": 23,
    "0.1.9": 19,
    "0.2.10-rc.1": 2,
    "0.2.42-dev.cefddd9": 5,
    "0.3.2-dev.ce5973c": 1,
    "0.0.2-alpha.63": 2,
    "0.3.0-rc.3": 2,
    "0.0.2-alpha.49": 3,
    "0.2.40-dev.a92120a": 3,
    "0.2.37-dev.91d5b2f": 2,
    "0.3.13-dev.07221a3": 1,
    "0.3.2-dev.05fc744": 1,
    "0.3.3-dev.52a641c": 1,
    "0.2.39-dev.cf281ef": 2,
    "0.1.4": 4,
    "0.2.38-dev.b858f84": 2,
    "0.1.0-alpha.50": 3,
    "0.3.13-dev.a868979": 1,
    "0.2.40-dev.1588c58": 3,
    "0.3.0-rc.24": 1,
    "0.3.11-dev.66acec8": 2,
    "0.2.42-dev.2bf93d4": 3,
    "0.3.12-dev.3e1caf0": 2,
    "0.3.12-dev.c77c43e": 4,
    "0.2.37-dev.ab39066": 3,
    "0.3.11-dev.2473ff0": 2,
    "0.1.0-alpha.28": 2,
    "0.0.2-alpha.23": 2,
    "0.0.2-alpha.62": 2,
    "0.2.0-alpha.34": 2,
    "0.2.36-dev.0d90bcd": 2,
    "0.3.13-dev.58fc088": 51,
    "0.3.0-rc.8": 3,
    "0.3.0-alpha.8": 3,
    "0.3.0-alpha.10": 2,
    "0.0.4": 4,
    "0.3.13-dev.af4f15c": 1,
    "0.2.0-alpha.23": 3,
    "0.2.36-dev.62d7976": 2,
    "0.3.3-dev.2b83776": 1,
    "0.2.43-dev.a5493fb": 2,
    "0.3.20-dev.62f574b": 7,
    "0.0.2-alpha.42": 2,
    "0.2.36": 5924,
    "0.2.19": 2273,
    "0.0.2-alpha.10": 2,
    "0.3.8-dev.bb33cd0": 2,
    "0.3.7-dev.60a7960": 3,
    "0.2.43-dev.96aed8a": 5,
    "0.2.44-dev.7facbab": 3,
    "0.0.2-alpha.58": 2,
    "0.2.3": 85,
    "0.3.15": 28136,
    "0.3.18-dev.173910e": 7,
    "0.0.2-alpha.69": 2,
    "0.3.5-dev.1693a17": 2,
    "0.2.41-dev.32bf6c0": 2,
    "0.2.36-dev.76e7ed94": 3,
    "0.3.18-dev.ebd61d1": 3,
    "0.1.0-alpha.45": 2,
    "0.3.3-dev.a641c5d": 2,
    "0.3.6-dev.7dfb69f": 3,
    "0.0.3-alpha.18": 2,
    "0.3.0-rc.28": 2,
    "0.3.12-dev.6c928a4": 8,
    "0.3.8-dev.109c1fa": 1,
    "0.2.42-dev.e0adeee": 3,
    "0.3.4-dev.17d391c": 1,
    "0.2.0-alpha.24": 3,
    "0.2.22-rc.2": 2,
    "0.3.11-dev.81fc9a9": 4,
    "0.2.40-dev.ae858ad": 2,
    "0.2.44-dev.8742e33": 2,
    "0.0.7-alpha.15": 2,
    "0.2.45-dev.33b2bd7": 45,
    "0.0.2-alpha.55": 2,
    "0.3.12-dev.12fdd73": 4,
    "0.0.2-alpha.5": 2,
    "0.3.0-rc.1": 4,
    "0.2.0-alpha.25": 2,
    "0.3.18-dev.48f5f85": 4,
    "0.0.5-alpha.5": 2,
    "0.2.0-alpha.19": 2,
    "0.3.0-rc.19": 107,
    "0.3.0-alpha.24": 527,
    "0.1.0-alpha.27": 2,
    "0.1.0-alpha.1": 11,
    "0.3.12-dev.8668c29": 1,
    "0.3.6-dev.cf3efec": 1,
    "0.2.45-dev.0fc093d": 3,
    "0.2.39-dev.e4d4636": 3,
    "0.3.16-dev.3d67901": 4,
    "0.3.16-dev.54f4f89": 4,
    "0.2.2": 9,
    "0.3.2-dev.edf27d9": 2,
    "0.0.7-alpha.7": 2,
    "0.0.2-alpha.50": 2,
    "0.1.20": 177,
    "0.0.9-alpha.1": 2,
    "0.3.8": 395,
    "0.3.4-dev.68a5c23": 1,
    "0.2.37-dev.2344db6": 2,
    "0.3.10-dev.e3aac27": 1,
    "0.3.5-dev.b1a0107": 2,
    "0.0.7-alpha.17": 2,
    "0.3.18-dev.fbd45db": 5,
    "0.3.12-dev.18b659d": 2,
    "0.3.18-dev.ff6e875": 63,
    "0.2.37-dev.5714e8d": 3,
    "0.0.8-alpha.4": 2,
    "0.1.0-alpha.41": 3,
    "0.2.39-dev.6929ae3": 2,
    "0.0.3-alpha.4": 2,
    "0.3.0-rc.15": 3,
    "0.3.18-dev.6d5b5d9": 5,
    "0.2.31": 81415,
    "0.2.45-dev.ea16ac2": 38,
    "0.3.18-dev.b240d87": 4,
    "0.3.12-dev.7726f5a": 4,
    "0.3.8-dev.9f7fc14": 2,
    "0.0.7-alpha.24": 2,
    "0.2.0-alpha.30": 2,
    "0.3.11-dev.38e0eff": 2,
    "0.0.2-alpha.68": 2,
    "0.2.45-dev.f3cfdd2": 1,
    "0.2.39-dev.9692930": 2,
    "0.3.5-dev.9d1e246": 1,
    "0.2.0-alpha.7": 3,
    "0.3.7-dev.97e1dc1": 2,
    "0.0.3-alpha.13": 2,
    "0.0.7-alpha.20": 2,
    "0.3.0-rc.20": 2,
    "0.0.2-alpha.7": 2,
    "0.2.42-dev.90a8deb": 4,
    "0.3.12-dev.defb409": 1,
    "0.2.0-alpha.26": 2,
    "0.1.0-alpha.32": 8,
    "0.3.18-dev.e72a9da": 6,
    "0.0.2-alpha.48": 2,
    "0.0.2-alpha.32": 2,
    "0.3.0-alpha.21": 5,
    "0.2.37-dev.80cdf8f": 3,
    "0.3.11-dev.6ba48bd": 2,
    "0.3.8-dev.dadb658": 3,
    "0.2.0-alpha.44": 2,
    "0.1.0-alpha.37": 2,
    "0.3.18-dev.7adbc9b": 5,
    "0.1.0-alpha.23": 2,
    "0.3.7-dev.a748f3c": 3,
    "0.3.9": 18176,
    "0.3.11-dev.fc3b4f8": 2,
    "0.3.8-dev.5ebc626": 3,
    "0.2.39-dev.0adad88": 3,
    "0.3.0-alpha.1": 2,
    "0.2.42-dev.6316e26": 2,
    "0.2.42-dev.a11c50d": 5,
    "0.2.38-dev.324f1d8": 2,
    "0.3.1-dev.9f1b8e3": 2,
    "0.2.39-dev.dd94c9d": 2,
    "0.2.37-dev.4201938": 2,
    "0.0.5-alpha.12": 2,
    "0.3.0-rc.26": 2,
    "0.2.0-alpha.28": 2,
    "0.0.7-alpha.10": 3,
    "0.3.6": 35382,
    "0.2.16": 1030,
    "0.2.44-dev.6713a42": 4,
    "0.3.12-dev.74f7f79": 1,
    "0.3.6-dev.0659ec3": 2,
    "0.2.16-rc.1": 6,
    "0.2.0-alpha.21": 2,
    "0.2.45-dev.3131c5c": 11,
    "0.2.0-alpha.13": 26,
    "0.0.2-alpha.45": 2,
    "0.2.44-dev.5a71803": 2,
    "0.3.11-dev.6eb674b": 3,
    "0.0.2-alpha.9": 2,
    "0.2.0-alpha.43": 2,
    "0.2.37-dev.01a038c": 3,
    "0.2.39-dev.4ad3a61": 2,
    "0.0.2-alpha.1": 2,
    "0.3.6-dev.bbdc20f": 1,
    "0.2.42-dev.6523fcc": 3,
    "0.3.18-dev.a00b1df": 5,
    "0.0.2": 7,
    "0.2.45-dev.32549fe": 2,
    "0.3.5-dev.ec27803": 2,
    "0.3.8-dev.fd7ae97": 2,
    "0.3.0-rc.32": 6,
    "0.3.20-dev.8ebe769": 7,
    "0.0.3-alpha.12": 2,
    "0.1.0-alpha.5": 2,
    "0.3.13-dev.97280fc": 2,
    "0.3.11-dev.2e1c9fd": 3,
    "0.3.18-dev.9471bfc": 3,
    "0.3.0-rc.7": 2,
    "0.3.6-dev.07f4537": 2,
    "0.0.5": 7,
    "0.2.44": 42709,
    "0.0.7-alpha.19": 2,
    "0.1.0-alpha.15": 2,
    "0.0.2-alpha.41": 2,
    "0.3.0-rc.41": 2,
    "0.0.2-alpha.40": 2,
    "0.1.1": 7,
    "0.3.7-dev.ec05f1d": 2,
    "0.3.13-dev.1fcd9f3": 1,
    "0.3.12-dev.0d72317": 18,
    "0.1.0-alpha.17": 3,
    "0.1.0-alpha.47": 3,
    "0.2.39-dev.d8c5812": 3,
    "0.2.0-alpha.5": 2,
    "0.3.7-dev.ec23922": 2,
    "0.0.3-alpha.6": 2,
    "0.2.40-dev.969af95": 2,
    "0.3.12-dev.0eb7441": 3,
    "0.2.26": 7018,
    "0.2.43": 15086,
    "0.2.10": 19,
    "0.2.15-rc.2": 8,
    "0.2.6": 150,
    "0.2.42-dev.baa5880": 3,
    "0.0.7-alpha.21": 2,
    "0.2.39-dev.2c861af": 2,
    "0.2.41-dev.4e7d32f": 2,
    "0.2.42-dev.d10484e": 6,
    "0.3.11-dev.85fa9c6": 2,
    "0.3.12-dev.9bd3a64": 2,
    "0.3.2-dev.28309eb": 2,
    "0.1.0-alpha.10": 2,
    "0.3.6-dev.862a402": 3,
    "0.3.8-dev.72728f1": 1,
    "0.3.8-dev.b8d04dc": 1,
    "0.2.22": 12748,
    "0.3.0-rc.13": 9,
    "0.3.17-dev.7108cc6": 5,
    "0.0.7-alpha.5": 2,
    "0.2.43-dev.4590c9b": 3,
    "0.3.18-dev.d184d85": 11,
    "0.2.42-dev.92c3e79": 2,
    "0.2.9-rc.1": 2,
    "0.3.13-dev.f1330ad": 1,
    "0.2.42-dev.02400da": 3,
    "0.3.0-rc.18": 2,
    "0.2.0-alpha.20": 2,
    "0.3.12-dev.6fb2121": 2,
    "0.1.14": 45,
    "0.3.18-dev.7e9cead": 5,
    "0.3.4-dev.4b37030": 1,
    "0.3.8-dev.46d0021": 1,
    "0.0.5-alpha.8": 2,
    "0.2.39-dev.bc55836": 2,
    "0.3.8-dev.bd96e27": 1,
    "0.1.0-alpha.14": 3,
    "0.3.18-dev.3cf938e": 5,
    "0.0.3-alpha.16": 2,
    "0.1.0-alpha.13": 25,
    "0.1.0-alpha.46": 2,
    "0.0.7-alpha.4": 16,
    "0.2.18": 7628,
    "0.3.20-dev.f232ba7": 7,
    "0.2.8": 72,
    "0.2.0-alpha.22": 2,
    "0.0.2-alpha.4": 2,
    "0.2.41-dev.1f558b1": 3,
    "0.2.5": 169,
    "0.2.41-dev.2d0abe7": 3,
    "0.2.42-dev.e52b26c": 2,
    "0.0.9": 23,
    "0.0.9-alpha.3": 2,
    "0.3.0-alpha.11": 32,
    "0.2.38-dev.02f0bce": 2,
    "0.3.16-dev.f5b93c1": 3,
    "0.3.12-dev.63ab05f": 2,
    "0.3.16-dev.8795c86": 4,
    "0.3.7-dev.1b5aa62": 2,
    "0.3.20-dev.1b34c9a": 8,
    "0.3.16-dev.21a9d67": 5,
    "0.3.6-dev.e296126": 3,
    "0.3.6-dev.4687be8": 1,
    "0.2.0-alpha.37": 2,
    "0.0.2-alpha.65": 2,
    "0.1.0-alpha.25": 2,
    "0.3.0-rc.23": 1,
    "0.2.0-alpha.10": 3,
    "0.3.20": 378176,
    "0.2.43-dev.6b0b15b": 3,
    "0.3.6-dev.1197d1d": 2,
    "0.2.37-dev.65cbcc7": 27,
    "0.3.6-dev.49cbe23": 2,
    "0.1.0-alpha.4": 3,
    "0.0.2-alpha.2": 2,
    "0.0.2-alpha.24": 2,
    "0.3.18-dev.ad5bf11": 4,
    "0.0.2-alpha.29": 2,
    "0.0.2-alpha.12": 3,
    "0.3.18-dev.7a58bbf": 5,
    "0.2.0-alpha.38": 2,
    "0.2.41-dev.7b8a1e3": 4,
    "0.3.20-dev.fa86f6f": 4,
    "0.3.18-dev.dff2d53": 4,
    "0.3.6-dev.1b4cb00": 1,
    "0.3.6-dev.9adab34": 1,
    "0.1.3": 9,
    "0.3.13-dev.099fcd9": 6,
    "0.3.12-dev.c669f50": 5,
    "0.2.34": 37981,
    "0.3.18-dev.aa8d24c": 4,
    "0.3.20-dev.73e3b49": 3,
    "0.3.8-dev.7198a7a": 2,
    "0.2.41-dev.98d5f39": 4,
    "0.0.2-alpha.21": 2,
    "0.3.18-dev.b5ec088": 4,
    "0.2.15-rc.1": 4,
    "0.2.39-dev.4aaafdf": 3,
    "0.2.41-dev.b2c8168": 2,
    "0.2.42-dev.f224f24": 2,
    "0.1.0-alpha.6": 2,
    "0.2.35": 1491,
    "0.0.8": 7,
    "0.1.0-alpha.31": 5,
    "0.2.36-dev.d365acc": 4,
    "0.2.37-dev.ba366f2": 3,
    "0.2.45-dev.10f46d9": 37,
    "0.3.12-dev.a95bed7": 3,
    "0.2.38-dev.d8f6037": 3,
    "0.1.0-alpha.7": 3,
    "0.0.3-alpha.17": 2,
    "0.1.0-alpha.11": 2,
    "0.0.2-alpha.25": 2,
    "0.2.0-alpha.35": 2,
    "0.2.42-dev.d6043b7": 3,
    "0.3.3-dev.f010205": 3,
    "0.3.8-dev.15f90e0": 2,
    "0.3.7-dev.bcdddc3": 1,
    "0.2.37-dev.cd71f62": 2,
    "0.2.13": 304,
    "0.0.7-alpha.14": 3,
    "0.3.19": 96159,
    "0.3.17-dev.f5d4397": 3,
    "0.3.12-dev.15a4eb9": 2,
    "0.2.36-dev.b797781": 3,
    "0.3.11-dev.71efa8e": 2,
    "0.2.37-dev.5a3767f": 2,
    "0.0.3-alpha.14": 2,
    "0.2.42-dev.f8154eb": 4,
    "0.3.8-dev.2e67138": 2,
    "0.3.7": 41398,
    "0.2.35-rc.0": 2,
    "0.0.2-alpha.52": 2,
    "0.0.4-alpha.1": 2,
    "0.0.2-alpha.8": 3,
    "0.3.6-dev.cc5a5c1": 3,
    "0.2.42-dev.bd22dc3": 2,
    "0.1.13": 7,
    "0.1.0-alpha.8": 2,
    "0.3.18-dev.b8af97a": 4,
    "0.1.0-alpha.48": 2,
    "0.3.21-dev.3d55188": 4,
    "0.2.37-dev.a3a3284": 3,
    "0.3.5-dev.eacecce": 2,
    "0.3.5-dev.c5dfc11": 3,
    "0.2.40-dev.3f98197": 2,
    "0.4.0-alpha.1": 22,
    "0.2.12-rc.1": 3,
    "0.3.5-dev.7832a1a": 3,
    "0.2.40-dev.0334d10": 2,
    "0.3.0-rc.30": 1,
    "0.3.16-dev.96b7ee4": 4,
    "0.3.18-dev.fdb9866": 3,
    "0.0.2-alpha.38": 2,
    "0.1.12": 20,
    "0.2.37-dev.37bd012": 2,
    "0.3.2-dev.35106df": 1,
    "0.3.8-dev.eb8f0c6": 1,
    "0.2.0-alpha.29": 2,
    "0.3.18-dev.122c897": 5,
    "0.0.2-alpha.66": 2,
    "0.3.13-dev.4fa14e3": 3,
    "0.3.6-dev.9d331b1": 1,
    "0.2.42-dev.3286519": 2,
    "0.0.2-alpha.14": 2,
    "0.1.0-alpha.19": 2,
    "0.2.17": 1940,
    "0.3.12": 172864,
    "0.0.7-alpha.13": 2,
    "0.2.42-dev.1446e02": 4,
    "0.3.1-dev.d61f857": 1,
    "0.2.39-dev.2133ffe": 2,
    "0.0.3-alpha.3": 2,
    "0.2.40-dev.d039319": 2,
    "0.2.39": 5358,
    "0.2.29": 50932,
    "0.2.44-dev.3291524": 5,
    "0.3.0-alpha.13": 4,
    "0.3.16-dev.a188b1d": 4,
    "0.3.20-dev.0cab0dd": 5,
    "0.0.6-alpha.4": 2,
    "0.3.11-dev.4ec04fa": 16,
    "0.3.12-dev.8731858": 3,
    "0.2.37-dev.768b4fe": 2,
    "0.2.39-dev.179ae75": 2,
    "0.2.44-dev.948d328": 5,
    "0.3.20-dev.54d8d9e": 4,
    "0.0.6-alpha.3": 3,
    "0.0.2-alpha.39": 2,
    "0.3.15-dev.115059d": 1,
    "0.2.42-dev.a855b90": 2,
    "0.3.13-dev.f7f6817": 1,
    "0.0.7-alpha.23": 2,
    "0.0.2-alpha.6": 2,
    "0.3.18-dev.dd59524": 4,
    "0.2.43-dev.a24d48a": 3,
    "0.3.4-dev.c75bcae": 1
  },
  "end": "2024-03-04T04:45:09.635Z",
  "start": "2024-02-26T04:45:09.635Z"
}