{
  "package": "@storybook/addon-storyshots",
  "downloads": {
    "6.0.0-rc.28": 67,
    "3.1.7": 6,
    "6.0.11": 6,
    "5.1.0-alpha.31": 4,
    "6.0.0-rc.29": 2,
    "3.3.11": 5,
    "3.3.5": 5,
    "5.2.0-alpha.14": 2,
    "4.1.5-react-debug.1": 3,
    "5.0.0-beta.3": 2,
    "5.3.0-alpha.26": 2,
    "5.0.0-rc.2": 2,
    "6.0.0-alpha.26": 2,
    "5.2.0-beta.4": 4,
    "6.0.0-beta.44": 2,
    "6.3.0-rc.8": 1,
    "6.0.0-alpha.0": 704,
    "6.5.0-alpha.34": 82,
    "6.1.7": 59,
    "6.5.0-alpha.39": 111,
    "6.0.0-beta.41": 2,
    "7.0.0-beta.46": 1,
    "6.0.0-beta.14": 3,
    "3.4.0-alpha.0": 3,
    "5.3.0-alpha.1": 3,
    "6.1.4": 37,
    "6.4.0": 353,
    "4.1.6": 32,
    "6.0.21": 2557,
    "6.1.16": 761,
    "6.0.6": 16,
    "0.0.0-pr-24447-sha-dc0980d9": 1,
    "7.0.2": 45,
    "7.0.0-alpha.8": 1,
    "6.0.5": 100,
    "6.0.0-rc.18": 7,
    "3.3.4": 5,
    "5.3.0-rc.3": 4,
    "7.6.0-beta.2": 1,
    "6.2.0-beta.14": 2,
    "6.2.5": 194,
    "7.0.0-beta.61": 12,
    "5.2.0-beta.42": 3,
    "5.0.0-debug.2": 4,
    "5.0.9": 3,
    "7.0.0-beta.56": 51,
    "6.0.0-alpha.18": 3,
    "5.3.0-beta.29": 3,
    "6.0.14": 5,
    "5.0.0-rc.5": 4,
    "4.0.0-alpha.21": 461,
    "7.0.0-beta.44": 15,
    "6.0.0-beta.9": 3,
    "5.2.0-alpha.7": 2,
    "5.1.0-alpha.34": 3,
    "5.2.0-alpha.38": 2,
    "6.0.0-alpha.13": 2,
    "4.0.0-alpha.25": 5,
    "3.4.12": 1717,
    "6.3.11": 40,
    "6.5.2": 66,
    "3.2.0-alpha.10": 2,
    "6.1.0-alpha.28": 3,
    "7.0.6": 89,
    "5.2.0-alpha.32": 3,
    "5.1.0-alpha.16": 2,
    "6.1.1": 224,
    "7.6.0": 262,
    "6.5.7": 527,
    "5.0.8": 54,
    "6.0.20": 41,
    "6.0.0-beta.26": 3,
    "5.3.0-beta.8": 3,
    "5.2.0-rc.2": 3,
    "6.0.0-alpha.10": 3,
    "7.3.1": 157,
    "4.0.7": 11,
    "5.2.0-alpha.35": 3,
    "5.2.0-alpha.15": 2,
    "5.2.0-beta.45": 3,
    "5.0.0-alpha.4": 4,
    "7.5.1": 2474,
    "3.2.8": 24,
    "3.3.10": 7,
    "4.0.0-alpha.15": 2,
    "6.0.0-alpha.42": 4,
    "5.2.0-alpha.36": 3,
    "5.2.0-rc.9": 4,
    "5.2.0-alpha.17": 3,
    "0.0.0-pr-24956-sha-878677ed": 1,
    "6.3.4": 1903,
    "5.1.0-alpha.4": 4,
    "5.0.0-debug.0": 3,
    "3.2.14": 9,
    "6.0.0-beta.29": 3,
    "0.0.0-pr-25575-sha-8fad0180": 1,
    "6.0.0-alpha.2": 30,
    "5.1.3": 48,
    "5.3.0-alpha.4": 3,
    "6.0.0-alpha.20": 3,
    "6.1.0-beta.0": 3,
    "4.0.0-alpha.2": 4,
    "5.1.0-alpha.6": 3,
    "5.0.2": 6,
    "6.0.3": 15,
    "5.3.0-beta.2": 3,
    "6.0.7": 4,
    "6.5.0-rc.1": 1,
    "5.2.0-alpha.16": 3,
    "6.5.0-alpha.54": 7,
    "6.4.8": 887,
    "5.3.0-beta.15": 5,
    "7.0.0": 2,
    "6.5.13": 15913,
    "6.5.0-alpha.40": 2,
    "5.3.0-alpha.9": 2,
    "7.6.1": 254,
    "6.4.4": 669,
    "5.1.0-alpha.26": 2,
    "6.3.0-alpha.26": 1,
    "6.0.0-beta.43": 2,
    "5.3.0-alpha.47": 2,
    "6.1.0-beta.7": 39,
    "7.0.0-beta.47": 12,
    "7.0.0-beta.16": 27,
    "7.4.6": 3036,
    "3.1.4": 122,
    "5.1.0-beta.1": 11,
    "5.1.0-alpha.30": 3,
    "5.3.0-alpha.3": 3,
    "6.3.9": 1635,
    "6.2.0-alpha.0": 7,
    "5.3.9": 236,
    "5.1.0-alpha.28": 4,
    "7.6.10": 1765,
    "6.3.0-alpha.18": 1,
    "3.3.0": 5,
    "5.3.0-alpha.38": 4,
    "3.4.0-alpha.8": 3,
    "6.4.0-beta.5": 1,
    "6.0.0-rc.0": 20,
    "4.0.11": 48,
    "6.4.1": 194,
    "5.3.0-beta.23": 4,
    "5.3.0-beta.9": 3,
    "5.0.0-alpha.7": 3,
    "6.1.0-alpha.15": 3,
    "6.1.0-alpha.19": 4,
    "6.0.13": 6809,
    "6.2.1": 192,
    "3.3.14": 9,
    "5.3.0-alpha.27": 2,
    "4.1.1": 11,
    "6.0.0-beta.39": 4,
    "7.0.0-beta.9": 89,
    "5.2.0-beta.43": 4,
    "4.2.0-alpha.8": 3,
    "7.6.5": 195,
    "3.2.6": 6,
    "5.0.0-alpha.3": 4,
    "6.0.0-beta.15": 2,
    "6.4.0-rc.4": 1,
    "6.1.0-beta.6": 4,
    "7.0.0-beta.25": 285,
    "5.1.7": 7,
    "7.6.0-alpha.6": 1,
    "6.0.0-rc.30": 4,
    "4.1.0-alpha.2": 4,
    "3.4.0-alpha.3": 3,
    "6.1.0-alpha.4": 2,
    "4.2.0-alpha.1": 3,
    "4.2.0-alpha.11": 4,
    "6.5.11": 60,
    "6.1.0-alpha.10": 3,
    "3.4.3": 57,
    "6.3.0-alpha.33": 1,
    "5.0.0-debug.1": 4,
    "6.0.0-rc.12": 4,
    "6.0.0": 1087,
    "5.3.21": 22744,
    "4.0.0-alpha.20": 5,
    "6.0.0-alpha.1": 3,
    "5.3.0-rc.5": 3,
    "5.2.0-alpha.10": 4,
    "6.0.0-beta.25": 3,
    "5.1.0-rc.0": 3,
    "7.0.0-alpha.49": 4,
    "5.3.0-alpha.45": 3,
    "5.2.0-beta.29": 4,
    "3.3.8": 3,
    "4.0.10": 7,
    "6.1.0-alpha.16": 3,
    "4.0.0-alpha.12": 3,
    "3.0.0-rc.2": 4,
    "5.2.0-beta.32": 2,
    "7.0.0-beta.50": 153,
    "7.0.0-beta.43": 10,
    "5.3.7": 44,
    "5.3.6": 31,
    "7.0.0-beta.6": 21,
    "4.2.0-alpha.2": 3,
    "6.0.0-alpha.44": 3,
    "5.2.0": 11,
    "6.2.0-beta.3": 62,
    "7.4.3": 39,
    "4.1.4": 143,
    "3.1.5": 3,
    "6.0.0-beta.21": 4,
    "5.3.0-alpha.30": 2,
    "5.2.0-alpha.41": 2,
    "6.4.20": 1822,
    "5.0.0-alpha.10": 4,
    "4.0.0-alpha.10": 3,
    "5.1.1": 6,
    "5.1.0-alpha.24": 2,
    "6.1.0-alpha.7": 2,
    "6.0.12": 82,
    "4.0.0-alpha.7": 7,
    "6.0.0-alpha.6": 4,
    "4.0.0-alpha.18": 4,
    "7.0.0-beta.51": 4,
    "4.1.0-alpha.1": 2,
    "5.3.1": 5,
    "5.2.0-beta.16": 2,
    "6.3.12": 11236,
    "7.0.0-beta.53": 29,
    "6.0.17": 39,
    "7.6.15": 542,
    "6.0.10": 156,
    "6.3.0-alpha.23": 1,
    "5.3.0-alpha.22": 3,
    "5.2.0-rc.6": 3,
    "5.1.0-rc.5": 3,
    "6.2.0-alpha.6": 4,
    "6.3.3": 4799,
    "6.5.0-alpha.43": 40,
    "6.0.0-beta.40": 2,
    "6.2.0-alpha.33": 8,
    "3.4.0-rc.4": 3,
    "4.0.3": 6,
    "6.0.0-alpha.3": 3,
    "7.1.1": 176,
    "7.1.0-alpha.13": 1,
    "6.3.0-beta.10": 85,
    "5.2.0-beta.15": 4,
    "6.5.0-alpha.60": 1,
    "6.0.0-alpha.17": 2,
    "5.3.2": 62,
    "7.6.2": 36,
    "6.4.0-alpha.40": 26,
    "5.2.0-beta.20": 2,
    "4.0.2": 11,
    "6.2.0-alpha.20": 5,
    "5.0.0-alpha.2": 2,
    "5.3.0-alpha.25": 3,
    "6.0.0-rc.25": 3,
    "7.0.12": 89,
    "5.3.0-alpha.46": 3,
    "4.0.0-alpha.1": 2,
    "5.2.0-beta.19": 4,
    "5.0.0-rc.10": 3,
    "3.1.6": 5,
    "5.2.1": 2281,
    "5.3.0-rc.4": 3,
    "5.2.0-alpha.3": 3,
    "5.3.0-alpha.2": 3,
    "5.1.0-alpha.17": 3,
    "6.1.0-beta.4": 2,
    "6.0.0-rc.1": 4,
    "5.2.0-beta.38": 3,
    "3.2.0-alpha.8": 3,
    "3.4.10": 301,
    "5.3.0-alpha.7": 58,
    "6.5.0-alpha.49": 1,
    "5.2.0-alpha.43": 2,
    "6.5.0-alpha.11": 2,
    "5.2.0-alpha.39": 4,
    "6.5.0-alpha.30": 1,
    "5.0.0-rc.0": 3,
    "5.0.1": 11,
    "6.0.0-alpha.15": 3,
    "5.1.0-rc.3": 3,
    "6.0.0-alpha.4": 3,
    "6.3.0-alpha.19": 10,
    "6.1.9": 892,
    "5.2.0-alpha.44": 3,
    "4.0.0-rc.2": 2,
    "3.4.0-alpha.9": 2,
    "5.3.0-rc.8": 34,
    "5.2.0-alpha.9": 3,
    "3.3.1": 5,
    "5.2.0-alpha.33": 3,
    "3.2.11": 5,
    "5.2.0-alpha.5": 2,
    "6.2.0-rc.0": 1,
    "7.4.4": 1,
    "5.2.0-beta.41": 4,
    "5.3.0-alpha.39": 2,
    "6.0.0-beta.12": 2,
    "5.1.0-rc.1": 4,
    "6.0.9": 4,
    "3.2.4": 33,
    "6.2.0": 30,
    "5.1.0-beta.0": 32,
    "6.2.0-beta.1": 68,
    "5.3.0-beta.25": 5,
    "6.0.2": 11,
    "7.6.3": 517,
    "7.0.9": 392,
    "5.1.0-alpha.32": 3,
    "3.0.0-alpha.1": 2,
    "5.2.0-alpha.1": 2,
    "5.3.5": 14,
    "6.1.0-alpha.23": 7,
    "6.2.0-alpha.10": 4,
    "6.0.15": 5,
    "7.0.0-beta.40": 76,
    "5.0.0-beta.2": 3,
    "5.2.0-beta.8": 3,
    "3.2.3": 5,
    "7.5.0": 870,
    "6.2.0-alpha.2": 2,
    "6.0.0-beta.17": 3,
    "3.2.0-alpha.5": 3,
    "6.1.21": 5004,
    "7.0.27": 1136,
    "6.5.16": 80448,
    "5.0.0-alpha.1": 3,
    "4.2.0-alpha.9": 3,
    "6.1.0-alpha.17": 4,
    "6.1.0-beta.1": 3,
    "5.3.0-beta.27": 3,
    "6.1.0-alpha.33": 2,
    "6.0.0-rc.15": 3,
    "6.0.0-beta.32": 4,
    "6.0.22": 235,
    "3.4.11": 103,
    "0.0.0-pr-25079-sha-65111396": 1,
    "5.3.0-alpha.36": 3,
    "5.2.0-alpha.21": 2,
    "3.2.10": 4,
    "6.2.9": 11228,
    "6.2.0-alpha.30": 4,
    "5.3.0-beta.1": 2,
    "6.3.1": 360,
    "6.5.0-alpha.28": 23,
    "7.0.7": 192,
    "3.1.1": 5,
    "4.0.0-alpha.14": 5,
    "0.0.0-pr-24973-sha-64de488b": 1,
    "6.3.2": 830,
    "6.4.9": 11925,
    "5.2.2": 4,
    "6.4.0-alpha.1": 5,
    "3.3.9": 4,
    "3.3.13": 8,
    "5.1.0-alpha.18": 3,
    "5.2.0-alpha.18": 2,
    "6.2.0-alpha.25": 14,
    "4.0.0-alpha.13": 2,
    "6.5.0-alpha.23": 21,
    "0.0.0-pr-25827-sha-620cb807": 1,
    "6.0.0-rc.27": 3,
    "6.1.0-rc.2": 2,
    "5.2.0-beta.30": 4,
    "4.1.0-alpha.12": 3,
    "6.1.0-alpha.8": 3,
    "6.1.0-alpha.18": 3,
    "3.4.0-alpha.7": 5,
    "3.2.12": 5,
    "5.2.0-alpha.26": 3,
    "3.0.0-alpha.0": 3,
    "5.2.0-beta.7": 3,
    "0.0.0-pr-25004-sha-c5268c93": 1,
    "3.2.19": 4,
    "4.0.0-alpha.4": 28,
    "6.4.0-beta.26": 41,
    "7.3.2": 1272,
    "3.4.5": 3,
    "6.2.0-alpha.4": 2,
    "6.5.0-alpha.50": 1,
    "6.5.0-alpha.16": 7,
    "4.0.0-rc.6": 41,
    "6.4.0-alpha.30": 63,
    "3.3.0-rc.0": 4,
    "5.2.0-alpha.20": 3,
    "7.2.2": 97,
    "6.0.19": 60,
    "5.0.4": 7,
    "7.6.6": 2216,
    "4.0.0-alpha.24": 127,
    "6.5.3": 62,
    "5.3.0-alpha.11": 3,
    "5.3.0-alpha.5": 3,
    "7.0.0-beta.13": 77,
    "7.0.5": 29,
    "5.3.0-alpha.0": 4,
    "5.3.0-beta.19": 2,
    "6.4.0-rc.3": 2,
    "6.2.0-alpha.7": 4,
    "5.3.0-rc.14": 3,
    "5.2.0-beta.0": 2,
    "6.3.6": 3540,
    "6.1.19": 2165,
    "5.3.0-beta.17": 2,
    "5.1.0-alpha.5": 4,
    "5.3.0-alpha.34": 4,
    "4.0.0-rc.1": 4,
    "6.2.2": 29,
    "6.3.7": 6566,
    "5.2.3": 196,
    "6.2.0-beta.0": 34,
    "3.3.15": 154,
    "4.0.8": 14,
    "5.3.0-rc.1": 3,
    "6.0.0-beta.16": 4,
    "0.0.0-pr-24447-sha-d63baba1": 1,
    "6.0.28-alpha.3": 7,
    "6.0.0-beta.22": 3,
    "5.2.0-beta.22": 3,
    "5.3.4": 6,
    "7.6.17": 13524,
    "4.0.0-alpha.9": 7,
    "3.3.12": 7,
    "7.0.0-beta.34": 22,
    "6.1.3": 763,
    "5.3.11": 36,
    "6.1.0-rc.4": 2,
    "5.2.0-beta.21": 3,
    "6.0.0-beta.27": 4,
    "3.0.0-rc.3": 4,
    "5.2.0-beta.10": 3,
    "6.1.0-rc.1": 3,
    "5.2.0-alpha.27": 4,
    "7.0.0-alpha.39": 3,
    "0.0.0-pr-24844-sha-d241a3e8": 1,
    "7.0.0-beta.54": 107,
    "6.3.8": 4299,
    "5.3.20": 7,
    "4.1.13": 14,
    "6.1.0-alpha.20": 2,
    "6.0.0-alpha.40": 4,
    "6.1.0-alpha.25": 3,
    "6.2.0-alpha.8": 3,
    "6.4.0-beta.27": 12,
    "5.3.0-alpha.31": 3,
    "5.1.0-rc.2": 3,
    "5.2.0-alpha.31": 3,
    "6.2.0-alpha.14": 3,
    "3.0.0-alpha.5": 3,
    "5.3.0-beta.10": 4,
    "5.3.0-alpha.6": 4,
    "6.5.0-alpha.26": 7,
    "6.4.0-beta.19": 41,
    "7.1.0-alpha.42": 1,
    "6.5.0-alpha.36": 659,
    "6.3.0-alpha.21": 1,
    "6.4.0-beta.12": 1,
    "5.1.0-alpha.21": 3,
    "6.5.0-alpha.51": 5,
    "5.1.0-alpha.33": 2,
    "5.2.0-beta.3": 3,
    "6.0.0-alpha.25": 3,
    "4.2.0-alpha.4": 2,
    "6.5.0-alpha.7": 37,
    "6.0.0-beta.13": 2,
    "5.3.0-alpha.29": 2,
    "4.1.11": 23,
    "7.4.2": 873,
    "5.3.0-alpha.43": 3,
    "7.0.26": 1017,
    "7.0.24": 219,
    "6.0.0-alpha.30": 23,
    "5.2.0-alpha.12": 3,
    "5.3.12": 812,
    "5.3.19": 4417,
    "6.5.6": 1663,
    "6.1.0-rc.6": 4,
    "5.2.0-rc.10": 2,
    "6.2.0-alpha.9": 3,
    "5.1.0-alpha.10": 3,
    "6.0.26": 2587,
    "4.1.7": 137,
    "6.2.4": 432,
    "3.3.0-alpha.0": 2,
    "5.3.0-rc.7": 3,
    "6.0.0-alpha.46": 4,
    "5.3.0-alpha.17": 4,
    "6.0.0-alpha.24": 4,
    "6.5.5": 423,
    "4.0.4": 12,
    "5.0.0-rc.1": 4,
    "7.6.16": 2387,
    "4.0.0-alpha.16": 89,
    "7.0.0-beta.35": 1,
    "6.5.0-alpha.5": 2,
    "5.2.0-beta.26": 3,
    "5.2.0-rc.11": 2,
    "6.2.0-beta.4": 86,
    "7.0.0-beta.29": 13,
    "5.0.0-rc.11": 4,
    "3.2.3-alpha.0": 2,
    "6.1.0-alpha.24": 4,
    "7.0.0-alpha.10": 1,
    "6.0.18": 41,
    "4.0.0-rc.0": 5,
    "7.4.1": 83,
    "5.2.0-alpha.22": 3,
    "5.2.0-beta.37": 3,
    "5.2.0-rc.4": 2,
    "6.0.0-rc.3": 2,
    "6.2.0-alpha.22": 5,
    "3.4.2": 67,
    "5.2.7": 162,
    "5.1.0-alpha.20": 3,
    "6.2.0-alpha.18": 4,
    "5.3.0-alpha.21": 3,
    "5.0.7": 16,
    "6.0.0-beta.42": 3,
    "7.0.18": 3485,
    "5.3.0-rc.12": 2,
    "6.1.5": 199,
    "7.0.4": 48,
    "7.0.14": 118,
    "6.0.24": 5,
    "6.1.0-alpha.1": 3,
    "5.3.0-rc.10": 3,
    "5.2.0-beta.2": 3,
    "7.0.10": 133,
    "6.1.15": 2469,
    "4.0.0": 17,
    "6.1.8": 250,
    "7.6.8": 834,
    "5.3.8": 77,
    "6.0.0-alpha.5": 3,
    "3.0.0-rc.0": 2,
    "5.2.0-alpha.2": 3,
    "6.0.0-alpha.41": 3,
    "5.2.0-beta.18": 3,
    "6.2.0-beta.10": 48,
    "3.4.7": 68,
    "6.1.17": 1902,
    "6.3.10": 423,
    "6.1.0-rc.3": 3,
    "6.5.0-alpha.59": 2,
    "6.1.14": 2606,
    "6.0.0-alpha.31": 4,
    "5.3.0-beta.16": 3,
    "5.2.0-rc.0": 3,
    "5.1.0-alpha.7": 4,
    "6.1.0-alpha.35": 2,
    "6.1.12": 1314,
    "6.2.7": 125,
    "6.1.6": 540,
    "7.0.0-beta.48": 35,
    "5.0.0": 10,
    "3.4.1": 76,
    "7.5.3": 3058,
    "7.0.0-alpha.30": 1,
    "4.1.0-alpha.9": 2,
    "6.5.14": 6060,
    "6.1.0-alpha.21": 3,
    "5.1.0-alpha.40": 2,
    "3.4.4": 21,
    "4.1.16": 31,
    "4.1.5-react-debug.0": 3,
    "7.0.22": 71,
    "6.2.0-alpha.23": 15,
    "5.1.0-alpha.19": 4,
    "5.1.0-alpha.2": 3,
    "7.0.0-beta.41": 1,
    "5.0.0-rc.6": 5,
    "6.2.0-rc.1": 8,
    "4.1.0": 4,
    "7.0.3": 1,
    "5.2.0-alpha.6": 2,
    "5.0.0-debug.3": 2,
    "6.0.0-rc.5": 3,
    "5.1.11": 725,
    "5.0.3": 14,
    "6.3.0-beta.5": 9,
    "6.0.0-beta.19": 3,
    "3.2.6-alpha.0": 3,
    "6.0.0-rc.23": 3,
    "6.0.0-alpha.34": 5,
    "5.1.0-alpha.0": 4,
    "3.4.0-rc.3": 3,
    "6.3.0-beta.9": 1,
    "5.3.0-alpha.32": 3,
    "5.2.8": 1069,
    "5.3.14": 705,
    "5.2.0-beta.33": 23,
    "7.0.15": 20,
    "5.2.0-beta.48": 4,
    "4.2.0-alpha.5": 3,
    "6.1.0-alpha.12": 3,
    "6.0.0-alpha.36": 4,
    "6.4.0-alpha.32": 6,
    "5.1.0-alpha.8": 3,
    "6.0.0-alpha.27": 290,
    "6.4.10": 242,
    "3.1.2": 16,
    "3.2.15": 4,
    "6.4.15": 873,
    "6.2.0-alpha.19": 19,
    "5.0.0-rc.8": 3,
    "5.2.0-rc.5": 3,
    "6.0.0-beta.31": 2,
    "6.4.18": 2455,
    "5.0.6": 275,
    "6.0.0-rc.10": 3,
    "6.4.0-rc.7": 2,
    "5.2.0-alpha.40": 3,
    "5.0.0-beta.4": 3,
    "5.0.0-beta.1": 2,
    "5.3.0-beta.11": 4,
    "5.2.0-rc.1": 2,
    "4.0.0-alpha.11": 4,
    "6.4.19": 60465,
    "5.2.0-beta.23": 5,
    "6.0.0-beta.7": 5,
    "6.0.0-beta.20": 3,
    "6.0.28-alpha.0": 4,
    "5.3.0-alpha.42": 4,
    "6.2.0-alpha.11": 2,
    "4.1.14": 29,
    "5.3.13": 943,
    "6.3.0-rc.0": 32,
    "6.5.9": 8277,
    "4.2.0-alpha.10": 3,
    "6.0.0-alpha.45": 3,
    "7.0.0-beta.19": 77,
    "6.5.0-alpha.33": 1,
    "5.3.0-beta.21": 3,
    "0.0.0-pr-24948-sha-9cde885a": 1,
    "6.0.0-beta.33": 12,
    "4.1.12": 18,
    "7.1.0": 869,
    "3.3.2": 6,
    "5.3.0-beta.22": 3,
    "4.2.0-cra-debug.0": 3,
    "5.2.0-alpha.19": 3,
    "6.5.0-alpha.32": 1,
    "5.3.0-alpha.23": 3,
    "7.0.0-alpha.54": 1,
    "5.3.17": 1517,
    "4.2.0-alpha.7": 3,
    "3.4.6": 56,
    "7.0.8": 41,
    "7.6.0-beta.0": 1,
    "4.0.0-alpha.22": 4,
    "5.1.0-alpha.37": 3,
    "6.0.0-beta.28": 3,
    "5.3.0-rc.6": 3,
    "4.0.0-rc.4": 2,
    "5.3.0-beta.30": 5,
    "5.0.0-alpha.0": 4,
    "5.2.0-alpha.4": 3,
    "5.3.0-alpha.10": 3,
    "5.1.0-alpha.14": 4,
    "5.1.0-alpha.39": 14,
    "6.1.0-beta.5": 4,
    "5.3.0-alpha.28": 3,
    "6.1.18": 3018,
    "5.1.0-alpha.29": 3,
    "5.3.15": 7,
    "5.1.0-rc.4": 5,
    "6.5.0-alpha.12": 6,
    "5.1.0-alpha.11": 2,
    "3.4.0-alpha.4": 3,
    "5.3.0-beta.14": 3,
    "6.0.0-beta.30": 2,
    "0.0.0-pr-24447-sha-3011241c": 1,
    "3.4.0-rc.2": 3,
    "5.3.0": 60,
    "6.5.0-alpha.42": 27,
    "6.0.28-alpha.2": 3,
    "6.5.0-alpha.18": 1,
    "5.0.0-rc.4": 4,
    "6.0.0-beta.35": 4,
    "6.0.0-alpha.21": 3,
    "5.0.11": 912,
    "7.6.14": 4777,
    "7.6.12": 960,
    "6.1.11": 5695,
    "6.0.0-beta.37": 3,
    "5.3.0-alpha.35": 2,
    "7.0.25": 260,
    "6.0.28-alpha.1": 3,
    "5.2.0-alpha.28": 2,
    "6.0.0-beta.6": 4,
    "6.1.0-beta.3": 4,
    "5.2.0-beta.13": 3,
    "5.1.0-alpha.3": 4,
    "5.2.4": 24282,
    "5.3.0-alpha.33": 3,
    "6.5.4": 52,
    "7.2.0": 104,
    "7.1.0-alpha.39": 1,
    "6.2.0-alpha.28": 4,
    "5.3.0-rc.9": 5,
    "5.3.0-alpha.13": 4,
    "3.3.0-alpha.3": 3,
    "5.3.0-alpha.19": 3,
    "5.3.0-rc.0": 2,
    "7.5.2": 698,
    "6.2.0-alpha.21": 5,
    "7.4.5": 195,
    "7.6.0-alpha.4": 37,
    "3.4.0-alpha.2": 3,
    "5.3.0-alpha.15": 2,
    "6.2.0-alpha.15": 4,
    "5.2.0-alpha.8": 3,
    "0.0.0-pr-22499-sha-edffc853": 1,
    "5.2.5": 230,
    "6.3.13": 2109,
    "3.3.7": 4,
    "5.1.4": 14,
    "4.1.2": 77,
    "7.0.21": 23,
    "3.4.0": 21,
    "6.1.0-alpha.22": 4,
    "7.0.23": 2619,
    "3.3.0-alpha.6": 2,
    "6.2.0-alpha.32": 7,
    "6.0.0-beta.2": 2,
    "6.0.0-rc.21": 3,
    "7.4.0": 784,
    "6.5.0-alpha.41": 53,
    "6.4.2": 518,
    "4.1.0-alpha.4": 5,
    "4.0.0-alpha.17": 3,
    "6.4.3": 223,
    "7.0.0-beta.10": 42,
    "5.3.3": 40,
    "5.3.0-beta.13": 3,
    "6.1.0-rc.5": 2,
    "5.0.0-rc.9": 3,
    "6.1.0-alpha.11": 2,
    "6.2.0-beta.2": 12,
    "6.4.0-alpha.17": 1,
    "4.0.12": 17,
    "3.2.18": 16,
    "6.1.0-alpha.9": 4,
    "6.0.0-beta.1": 2,
    "6.0.4": 48,
    "5.0.0-alpha.11": 3,
    "5.3.0-beta.0": 3,
    "6.0.0-beta.18": 3,
    "5.2.0-alpha.23": 3,
    "6.0.1": 14,
    "6.1.2": 181,
    "6.4.0-beta.7": 7,
    "6.1.0": 92,
    "4.0.9": 16,
    "6.5.15": 17698,
    "6.2.0-alpha.29": 17,
    "6.2.0-alpha.16": 24,
    "7.0.0-beta.33": 22,
    "4.1.9": 13,
    "4.0.1": 12,
    "6.0.0-rc.20": 3,
    "3.2.0-alpha.7": 3,
    "6.0.0-alpha.19": 3,
    "7.0.0-beta.55": 159,
    "6.3.0": 635,
    "4.1.0-alpha.13": 3,
    "4.0.0-alpha.8": 57,
    "4.0.0-rc.3": 3,
    "6.2.0-alpha.17": 3,
    "6.0.28": 2152,
    "6.4.14": 2660,
    "3.2.17": 18,
    "4.1.3": 26,
    "5.3.0-alpha.12": 3,
    "4.0.0-alpha.3": 6,
    "6.0.0-rc.9": 3,
    "5.0.0-alpha.9": 4,
    "6.2.0-alpha.35": 4,
    "3.2.5": 3,
    "6.4.0-alpha.36": 5,
    "5.2.0-alpha.34": 2,
    "5.3.0-rc.13": 3,
    "4.0.0-alpha.6": 5,
    "7.0.0-rc.10": 1,
    "7.0.0-alpha.40": 26,
    "5.2.0-beta.9": 4,
    "5.1.0-alpha.9": 5,
    "6.0.0-alpha.28": 3,
    "5.3.0-beta.31": 4,
    "6.5.0-alpha.3": 10,
    "6.0.16": 1191,
    "6.0.0-rc.2": 3,
    "6.0.23": 5,
    "6.1.0-alpha.26": 3,
    "5.2.0-beta.28": 3,
    "6.0.0-alpha.9": 3,
    "5.2.0-alpha.11": 3,
    "6.2.0-alpha.12": 2,
    "5.2.0-alpha.30": 3,
    "5.3.0-alpha.18": 2,
    "3.4.0-alpha.5": 3,
    "6.3.0-alpha.14": 6,
    "6.4.0-alpha.16": 1,
    "6.2.0-alpha.34": 5,
    "6.5.10": 5471,
    "7.0.0-beta.39": 263,
    "6.2.0-rc.4": 1,
    "3.2.0-alpha.11": 2,
    "6.1.0-alpha.27": 3,
    "6.1.0-alpha.0": 3,
    "6.0.0-rc.13": 4,
    "6.0.0-beta.34": 4,
    "6.0.0-rc.8": 4,
    "6.0.27": 1035,
    "6.1.0-alpha.29": 4,
    "0.0.0-pr-24844-sha-520c653e": 1,
    "5.1.0-alpha.25": 3,
    "6.5.8": 16915,
    "6.4.17": 720,
    "6.4.7": 209,
    "6.0.0-alpha.22": 3,
    "6.0.0-beta.0": 4,
    "5.2.0-rc.8": 3,
    "3.4.0-alpha.6": 2,
    "5.2.0-beta.46": 3,
    "6.0.25": 237,
    "5.1.0-alpha.35": 3,
    "6.1.10": 2948,
    "7.6.13": 2496,
    "5.2.0-beta.5": 4,
    "6.1.0-alpha.34": 3,
    "5.2.0-beta.24": 3,
    "4.1.0-alpha.8": 3,
    "5.0.0-alpha.6": 3,
    "6.4.0-alpha.18": 1,
    "6.2.8": 557,
    "6.4.22": 11752,
    "7.0.0-alpha.34": 130,
    "5.2.0-beta.31": 2,
    "5.3.0-alpha.37": 3,
    "5.3.18": 12848,
    "6.1.20": 4960,
    "6.2.0-alpha.5": 17,
    "7.6.0-alpha.7": 1,
    "6.0.0-rc.24": 3,
    "6.0.0-rc.11": 4,
    "6.0.0-alpha.11": 3,
    "5.2.0-beta.25": 3,
    "6.1.0-alpha.30": 2,
    "7.6.9": 262,
    "7.2.1": 375,
    "6.3.0-beta.2": 1,
    "5.2.0-alpha.24": 2,
    "6.0.0-alpha.14": 3,
    "3.3.0-alpha.2": 3,
    "7.0.11": 122,
    "7.3.0": 337,
    "5.1.8": 34,
    "7.0.0-beta.62": 31,
    "5.2.0-beta.40": 3,
    "5.3.0-rc.11": 3,
    "6.1.0-alpha.14": 2,
    "6.0.0-alpha.12": 4,
    "5.3.0-alpha.40": 2,
    "7.6.0-beta.1": 1,
    "6.4.21": 5737,
    "3.4.0-rc.1": 2,
    "4.1.0-alpha.10": 4,
    "6.0.0-rc.16": 134,
    "4.0.0-rc.5": 2,
    "5.0.0-alpha.8": 3,
    "6.4.0-alpha.24": 1,
    "4.1.18": 1918,
    "4.0.6": 20,
    "6.4.5": 56,
    "5.3.0-beta.3": 45,
    "6.4.0-beta.25": 1,
    "3.0.0-alpha.4": 4,
    "6.5.0-alpha.61": 1,
    "6.0.0-rc.14": 19,
    "4.1.0-alpha.11": 2,
    "7.0.0-beta.36": 9,
    "5.2.0-alpha.13": 3,
    "7.6.0-alpha.5": 1,
    "6.4.13": 3857,
    "6.0.0-beta.8": 23,
    "6.2.3": 279,
    "3.3.0-alpha.4": 3,
    "6.0.0-alpha.8": 2,
    "5.0.0-rc.3": 4,
    "4.2.0-alpha.6": 4,
    "5.2.0-alpha.29": 3,
    "6.4.12": 1613,
    "7.0.0-rc.7": 1,
    "6.5.0": 13,
    "5.3.0-alpha.20": 3,
    "5.1.0-alpha.13": 4,
    "3.0.0-alpha.2": 4,
    "3.2.16": 85,
    "6.0.0-alpha.35": 2,
    "5.3.0-beta.18": 3,
    "6.5.0-alpha.55": 1,
    "6.3.0-alpha.8": 2,
    "3.1.8": 4,
    "6.1.0-alpha.31": 4,
    "5.3.0-beta.26": 3,
    "5.2.0-beta.12": 2,
    "5.1.0-alpha.1": 4,
    "6.0.0-beta.45": 6,
    "5.0.0-alpha.5": 4,
    "5.3.0-beta.28": 4,
    "3.3.3": 113,
    "6.0.0-beta.38": 11,
    "7.2.3": 215,
    "7.0.17": 437,
    "6.0.0-alpha.7": 4,
    "5.0.0-rc.7": 3,
    "4.2.0-alpha.3": 4,
    "5.3.0-alpha.24": 3,
    "6.2.0-alpha.27": 4,
    "6.1.0-beta.2": 4,
    "0.0.0-pr-22236-sha-107ce09c": 1,
    "7.0.0-alpha.33": 2,
    "7.6.11": 23,
    "5.1.5": 141,
    "4.1.0-alpha.3": 3,
    "5.1.0-alpha.15": 2,
    "6.4.0-beta.10": 44,
    "6.5.0-alpha.20": 1,
    "5.1.9": 1451,
    "7.0.0-alpha.47": 4,
    "5.2.0-alpha.37": 4,
    "7.0.0-rc.3": 6,
    "3.2.13": 53,
    "6.0.0-rc.22": 3,
    "6.1.0-rc.0": 4,
    "5.1.0-alpha.27": 4,
    "5.1.0-alpha.12": 3,
    "5.0.5": 72,
    "7.0.0-beta.8": 164,
    "4.0.0-alpha.23": 2,
    "6.5.12": 9981,
    "4.0.0-alpha.0": 3,
    "3.2.0-alpha.12": 2,
    "5.2.0-beta.47": 3,
    "6.0.0-rc.19": 4,
    "5.1.0-alpha.22": 3,
    "6.0.0-alpha.32": 3,
    "6.2.0-rc.11": 1,
    "6.2.0-alpha.1": 5,
    "5.0.10": 46,
    "7.6.7": 3389,
    "6.0.0-alpha.43": 3,
    "5.3.10": 15,
    "5.3.0-beta.12": 9,
    "6.2.0-alpha.31": 6,
    "5.2.0-beta.36": 3,
    "5.1.0-alpha.23": 4,
    "6.0.0-alpha.29": 3,
    "3.2.7": 4,
    "6.2.0-alpha.24": 16,
    "6.0.0-beta.24": 4,
    "6.5.0-alpha.22": 23,
    "5.2.0-beta.6": 4,
    "6.0.0-rc.26": 2,
    "5.2.0-beta.39": 3,
    "5.3.0-beta.6": 4,
    "7.0.0-beta.31": 45,
    "6.0.0-beta.3": 94,
    "3.0.0": 18,
    "3.4.0-rc.0": 4,
    "3.4.8": 114,
    "6.0.0-beta.46": 2,
    "6.5.0-alpha.9": 41,
    "6.1.0-alpha.6": 4,
    "5.2.0-beta.14": 4,
    "6.1.0-alpha.32": 4,
    "6.0.0-alpha.37": 4,
    "3.4.0-alpha.1": 3,
    "5.3.0-beta.20": 2,
    "4.1.0-alpha.7": 4,
    "0.0.0-pr-24447-sha-da48fb11": 1,
    "0.0.0-pr-24948-sha-12960c76": 1,
    "5.2.0-beta.1": 4,
    "6.0.0-beta.5": 3,
    "0.0.0-pr-24959-sha-01ff0210": 1,
    "7.0.0-beta.52": 23,
    "6.0.0-beta.23": 48,
    "0.0.0-pr-24975-sha-7ac48cba": 1,
    "7.0.0-beta.45": 41,
    "6.2.0-alpha.26": 4,
    "6.0.0-beta.4": 3,
    "6.0.0-alpha.33": 2,
    "5.2.0-alpha.42": 3,
    "6.4.16": 11,
    "3.1.0": 4,
    "3.1.9": 7,
    "5.3.0-alpha.41": 3,
    "6.5.0-alpha.44": 60,
    "5.2.0-beta.17": 4,
    "6.0.0-alpha.39": 3,
    "5.1.0-alpha.36": 5,
    "6.2.0-alpha.13": 2,
    "6.2.0-alpha.3": 2,
    "5.2.0-alpha.0": 3,
    "3.3.6": 3,
    "5.2.6": 1500,
    "7.6.4": 9698,
    "6.1.0-alpha.3": 3,
    "3.3.0-rc.1": 4,
    "6.2.6": 23,
    "3.2.0": 4,
    "5.1.10": 695,
    "7.0.20": 763,
    "6.3.5": 251,
    "0.0.0-pr-24948-sha-038ec6fd": 1,
    "0.0.0-pr-24447-sha-191688a0": 1,
    "6.0.0-beta.36": 3,
    "3.0.0-alpha.3": 4,
    "7.0.0-beta.38": 1,
    "5.3.0-alpha.44": 4
  },
  "end": "2024-03-04T04:45:48.670Z",
  "start": "2024-02-26T04:45:48.670Z"
}