{
  "package": "gulp-bump",
  "downloads": {
    "1.0.0": 2246,
    "2.4.0": 108,
    "0.1.8": 9,
    "3.1.3": 3205,
    "2.9.0": 9475,
    "0.1.0": 5,
    "0.0.1": 7,
    "0.1.1": 5,
    "0.1.2": 9,
    "0.1.7": 4,
    "0.1.3": 5,
    "2.6.0": 3,
    "2.5.0": 30,
    "0.1.11": 7,
    "0.0.4": 4,
    "3.1.1": 309,
    "3.1.2": 18,
    "0.3.1": 1912,
    "0.2.0": 4,
    "2.6.1": 16,
    "0.2.1": 4,
    "2.2.0": 80,
    "2.7.0": 1041,
    "0.1.6": 5,
    "0.1.5": 5,
    "0.1.4": 5,
    "3.1.0": 170,
    "3.0.0": 95,
    "0.1.10": 5,
    "0.0.3": 5,
    "0.0.7": 5,
    "2.0.1": 162,
    "0.1.9": 20,
    "0.0.6": 5,
    "0.1.13": 618,
    "0.0.2": 5,
    "2.0.0": 2,
    "0.2.2": 251,
    "0.0.5": 5,
    "3.2.0": 11598,
    "0.0.8": 5,
    "2.1.0": 166,
    "2.5.1": 106,
    "2.8.0": 375,
    "0.3.0": 17
  },
  "end": "2024-03-04T04:47:06.145Z",
  "start": "2024-02-26T04:47:06.145Z"
}