{
  "package": "postcss-normalize-positions",
  "downloads": {
    "5.0.3": 172237,
    "6.0.0": 837019,
    "4.0.0-nightly.2020.9.1": 2,
    "4.0.0-nightly.2020.9.3": 2,
    "5.0.2": 144075,
    "4.0.0-nightly.2020.7.31": 2,
    "6.0.1": 1351952,
    "5.0.0-rc.1": 17,
    "4.0.0-nightly.2020.10.20": 2,
    "4.0.0-nightly.2020.8.10": 2,
    "5.0.0-rc.2": 284,
    "4.0.0-nightly.2020.9.9": 2,
    "4.0.0-nightly.2020.7.24": 2,
    "5.0.4": 547122,
    "4.0.0-nightly.2020.8.25": 2,
    "4.0.0-nightly.2020.7.25": 2,
    "4.0.0-nightly.2020.8.4": 2,
    "4.0.0-nightly.2020.8.29": 2,
    "4.0.0-nightly.2020.8.17": 3,
    "5.1.1": 7014836,
    "4.0.0": 6025,
    "4.0.0-nightly.2020.1.11": 2,
    "5.0.0": 39355,
    "4.0.0-nightly.2020.2.6": 175,
    "4.0.0-nightly.2020.1.9": 2,
    "4.0.2": 8326270,
    "4.0.0-rc.2": 254,
    "4.0.0-nightly.2020.8.1": 2,
    "4.0.0-rc.0": 27,
    "4.0.0-nightly.2020.8.24": 2,
    "5.1.0": 678521,
    "4.0.1": 65283,
    "5.0.0-rc.0": 34,
    "5.0.1": 764564
  },
  "end": "2024-03-04T04:46:57.625Z",
  "start": "2024-02-26T04:46:57.625Z"
}