{
  "package": "primeng",
  "downloads": {
    "8.0.3": 992,
    "8.1.1": 12582,
    "16.9.0": 535,
    "17.4.0": 5831,
    "11.4.5": 19918,
    "12.2.0": 908,
    "13.3.3": 3099,
    "1.0.0-beta.8": 19,
    "1.0.1": 23,
    "17.3.2": 2682,
    "17.9.0": 5852,
    "1.0.0-beta.19": 1,
    "1.1.4": 1226,
    "8.0.1": 681,
    "7.0.0-rc.2": 60,
    "16.1.0": 11159,
    "6.0.0-alpha.1": 208,
    "4.3.0-rc.1": 168,
    "8.1.4": 2517,
    "16.8.0": 1004,
    "13.3.1": 161,
    "4.2.1": 6968,
    "11.3.0-rc.1": 196,
    "4.1.3": 2801,
    "4.2.0-rc.1": 427,
    "6.1.7": 6085,
    "16.0.0-rc.1": 301,
    "1.0.0-rc.4": 1,
    "1.0.0-rc.6": 4834,
    "14.0.2": 4345,
    "0.2.0": 7,
    "16.9.4-lts": 6,
    "7.1.0": 1155,
    "16.4.3": 715,
    "15.4.16-lts": 150,
    "4.0.0-rc.1": 2256,
    "13.4.1": 34200,
    "15.1.1": 3489,
    "0.7.0": 8,
    "12.1.1": 1447,
    "15.4.14-lts": 23,
    "16.5.0": 1794,
    "11.2.3": 5726,
    "0.8.1": 9,
    "16.4.0": 891,
    "14.2.6-lts": 3,
    "9.1.0": 1508,
    "13.0.0-rc.2": 310,
    "15.4.3-lts": 10,
    "5.0.0-rc.0": 5,
    "11.1.0-rc.1": 733,
    "11.3.2": 2019,
    "1.1.2": 44,
    "8.1.0": 495,
    "15.1.0": 317,
    "1.0.0-beta.13": 82,
    "12.2.2": 2126,
    "14.0.1": 1396,
    "16.0.0-rc.2": 989,
    "6.1.4": 955,
    "6.1.6": 1165,
    "5.2.4": 2359,
    "14.0.0-rc.1": 342,
    "2.0.5": 787,
    "17.0.0-beta.1": 768,
    "9.0.2": 688,
    "13.3.0": 1038,
    "7.0.1": 59,
    "13.0.0-rc.1": 50,
    "0.5.0": 4,
    "17.3.1": 2400,
    "8.0.0": 962,
    "10.0.0-rc.4": 62,
    "1.0.0-rc.1": 3,
    "9.0.0-rc.2": 530,
    "16.7.0": 610,
    "1.0.0-beta.12": 79,
    "1.0.0-beta.9": 7,
    "8.1.3": 29,
    "9.1.2": 667,
    "5.2.0-rc.1": 2459,
    "16.0.2": 7023,
    "14.2.0": 123,
    "17.5.0": 2958,
    "16.0.1": 1850,
    "13.2.1": 3847,
    "0.8.2": 4,
    "13.2.0": 5510,
    "4.0.0-rc.4": 205,
    "7.0.0": 838,
    "2.0.0-rc.1": 55,
    "12.1.0": 846,
    "5.2.6": 335,
    "13.0.3": 859,
    "2.0.0-rc.2": 972,
    "13.4.2-lts": 5,
    "14.1.2": 9399,
    "14.2.11-lts": 2,
    "15.4.8-lts": 8,
    "1.0.0-beta.11": 5,
    "13.0.2": 1246,
    "6.0.1": 234,
    "6.1.1": 55,
    "1.0.0-beta.6": 5,
    "14.2.7-lts": 21,
    "15.4.1": 38702,
    "16.7.1": 835,
    "5.0.0": 105,
    "17.2.0": 1955,
    "14.2.13-lts": 80,
    "10.0.0-rc.3": 576,
    "11.4.2": 2486,
    "11.1.0": 1551,
    "7.1.3": 10374,
    "12.2.0-rc.1": 89,
    "14.2.8-lts": 174,
    "11.2.2": 621,
    "13.1.0": 3570,
    "5.0.1": 164,
    "5.2.2": 455,
    "1.0.0-beta.4": 5,
    "8.0.4": 952,
    "4.1.0-rc.3": 1303,
    "1.0.0-beta.5": 6,
    "9.1.3": 27460,
    "16.3.0": 50,
    "15.2.1": 2395,
    "15.4.9-lts": 302,
    "1.0.0-beta.14": 34,
    "11.4.0": 1520,
    "1.0.0-rc.2": 2,
    "5.0.2": 3967,
    "5.2.0": 1611,
    "2.0.3": 827,
    "15.4.7-lts": 9,
    "4.1.2": 3538,
    "16.0.0": 631,
    "1.0.0-beta.1": 5,
    "4.3.0": 10984,
    "6.1.2": 350,
    "17.6.0": 5111,
    "2.0.1": 13003,
    "16.3.1": 10181,
    "7.0.2": 74,
    "5.2.5": 387,
    "13.0.1": 295,
    "13.0.4": 3342,
    "8.0.2": 995,
    "0.9.1": 5,
    "4.0.3": 918,
    "6.1.5": 970,
    "16.4.1": 2696,
    "4.0.0-rc.5": 329,
    "11.2.1": 546,
    "1.0.0-beta.16": 22,
    "15.2.0": 17772,
    "14.0.0": 4346,
    "4.0.0-rc.3": 614,
    "11.3.0": 349,
    "16.6.0": 2911,
    "1.0.0-beta.15": 14,
    "16.9.3-lts": 237,
    "14.2.1": 899,
    "11.3.1": 1015,
    "15.4.12-lts": 5,
    "9.1.1": 5,
    "1.1.0": 217,
    "13.4.0": 900,
    "10.0.0-rc.1": 32,
    "9.0.3": 257,
    "8.0.0-rc.1": 90,
    "16.2.0": 4888,
    "5.2.7": 6992,
    "1.0.0-beta.10": 6,
    "15.4.4-lts": 52,
    "14.2.2": 6852,
    "13.1.1": 3795,
    "10.0.0": 2241,
    "14.2.17-lts": 421,
    "14.2.5-lts": 33,
    "4.2.0": 2587,
    "12.0.2": 1837,
    "0.3.0": 7,
    "5.2.1": 161,
    "6.0.0-beta.1": 273,
    "6.1.0": 500,
    "12.0.1": 1758,
    "1.0.0-beta.20": 4,
    "15.4.13-lts": 799,
    "2.0.0-rc.3": 6354,
    "17.8.0": 16246,
    "1.0.0-beta.17": 6,
    "6.0.0-rc.1": 98,
    "14.2.12-lts": 60,
    "11.0.0-rc.1": 412,
    "1.0.0": 504,
    "15.4.11-lts": 84,
    "6.0.0-alpha.2": 7,
    "14.2.15-lts": 2,
    "9.0.1": 191,
    "4.2.2": 3325,
    "16.9.2-lts": 8,
    "14.2.14-lts": 23,
    "10.0.3": 12666,
    "5.2.3": 2169,
    "15.0.1": 4056,
    "14.1.0": 893,
    "5.2.0-rc.2": 5669,
    "15.4.6-lts": 30,
    "7.0.0-beta.1": 160,
    "16.9.5-lts": 259,
    "1.1.1": 286,
    "1.0.0-rc.3": 6,
    "9.0.4": 217,
    "14.2.16-lts": 2,
    "0.1.0": 10,
    "16.7.2": 1067,
    "12.2.3": 17569,
    "13.4.4-lts": 27,
    "15.4.15-lts": 27,
    "0.8.0": 6,
    "0.6.0": 17,
    "9.0.6": 2388,
    "12.0.0-rc.1": 229,
    "15.0.0-rc.1": 679,
    "4.1.1": 2355,
    "12.1.0-rc.1": 231,
    "2.0.4": 155,
    "17.0.0-rc.1": 810,
    "9.0.0": 3018,
    "7.0.3": 362,
    "12.0.0": 1958,
    "9.0.5": 1729,
    "12.2.1": 1778,
    "16.4.2": 1326,
    "15.4.10-lts": 55,
    "0.9.0": 5,
    "14.2.10-lts": 8,
    "2.0.2": 583,
    "15.4.0": 245,
    "1.0.0-rc.5": 52,
    "4.0.1": 9778,
    "10.0.1": 40,
    "15.4.5-lts": 22,
    "1.1.3": 1793,
    "10.0.2": 837,
    "1.0.0-beta.2": 5,
    "11.4.1": 401,
    "2.0.0": 3617,
    "7.0.0-rc.1": 8,
    "7.1.2": 308,
    "6.0.0": 1333,
    "11.0.0-rc.2": 196,
    "17.0.0": 1741,
    "9.0.0-rc.4": 521,
    "4.1.0-rc.2": 5444,
    "13.0.0": 880,
    "4.3.0-rc.2": 7,
    "4.1.0-rc.1": 2,
    "2.0.6": 673,
    "14.2.3": 33149,
    "16.9.1": 25916,
    "6.0.2": 161,
    "9.0.0-rc.3": 42,
    "17.3.3": 3386,
    "4.1.0": 7719,
    "7.0.4": 397,
    "7.1.1": 130,
    "17.3.0": 1682,
    "11.4.3": 1368,
    "11.0.0": 1870,
    "6.1.3": 647,
    "4.0.2": 8,
    "11.2.0": 3747,
    "15.3.0": 5123,
    "0.4.0": 4,
    "12.1.0-rc.2": 217,
    "4.0.0": 4113,
    "1.0.0-beta.3": 4,
    "6.1.0-rc.1": 16,
    "14.1.1": 1969,
    "13.4.3-lts": 6,
    "4.0.0-rc.2": 3052,
    "7.0.5": 995,
    "13.3.2": 654,
    "16.5.1": 4850,
    "15.0.0": 2404,
    "17.1.0": 2287,
    "10.0.0-rc.2": 35,
    "13.4.5-lts": 32,
    "11.4.4": 1940,
    "9.0.0-rc.1": 93,
    "17.7.0": 12061,
    "1.0.0-rc.7": 2,
    "14.2.4-lts": 82,
    "14.2.9-lts": 1,
    "1.0.0-beta.7": 6,
    "15.4.2-lts": 8,
    "7.1.0-rc.1": 83
  },
  "end": "2024-03-04T04:45:22.844Z",
  "start": "2024-02-26T04:45:22.844Z"
}