{
  "package": "@babel/plugin-transform-unicode-escapes",
  "downloads": {
    "7.14.5": 1886108,
    "7.12.13": 2611344,
    "7.12.1": 1635570,
    "7.21.5": 714625,
    "8.0.0-alpha.7": 130,
    "7.16.7": 4523300,
    "8.0.0-alpha.6": 149,
    "7.21.4-esm": 10,
    "7.18.10": 7816008,
    "7.10.1": 241972,
    "7.21.4-esm.1": 10,
    "7.21.4-esm.4": 10,
    "8.0.0-alpha.5": 983,
    "8.0.0-alpha.1": 11,
    "8.0.0-alpha.2": 16,
    "8.0.0-alpha.0": 39,
    "7.10.4": 928186,
    "7.18.6": 655007,
    "8.0.0-alpha.3": 43,
    "7.22.5": 1372815,
    "7.10.0": 11823,
    "7.21.4-esm.3": 18,
    "7.23.3": 10120678,
    "7.16.0": 843011,
    "7.21.4-esm.2": 19,
    "8.0.0-alpha.4": 90,
    "7.22.10": 2754035,
    "7.16.5": 366926
  },
  "end": "2024-03-04T04:42:05.074Z",
  "start": "2024-02-26T04:42:05.074Z"
}