{
  "package": "ndarray",
  "downloads": {
    "0.2.4": 61,
    "1.0.12": 4,
    "0.2.3": 3,
    "1.0.18": 67410,
    "1.0.1": 5,
    "1.0.5": 2,
    "1.0.13": 7,
    "0.0.0": 2,
    "1.0.8": 2,
    "1.0.0": 3,
    "1.0.19": 756568,
    "0.0.2": 2,
    "1.0.6": 2,
    "0.2.0": 2,
    "0.0.1": 2,
    "0.2.2": 2,
    "0.2.1": 2,
    "1.0.16": 9,
    "1.0.9": 11,
    "1.0.2": 1,
    "1.0.10": 4,
    "1.0.14": 4,
    "1.0.17": 10,
    "1.0.4": 5,
    "1.0.15": 4,
    "1.0.3": 2,
    "1.0.11": 19
  },
  "end": "2024-03-04T04:45:11.050Z",
  "start": "2024-02-26T04:45:11.050Z"
}