{
  "package": "markdown-it",
  "downloads": {
    "8.3.0": 40,
    "9.0.1": 8697,
    "4.0.0": 8,
    "12.3.1": 2689,
    "6.0.1": 4086,
    "2.1.2": 4,
    "8.4.1": 12000,
    "12.1.0": 9455,
    "6.0.3": 5,
    "12.0.4": 163727,
    "12.2.0": 97189,
    "12.0.2": 36673,
    "6.0.5": 146,
    "2.0.0": 4,
    "6.0.2": 61,
    "4.0.3": 1064,
    "3.0.2": 5,
    "4.2.2": 7,
    "4.2.1": 52,
    "13.0.0": 3541,
    "10.0.0": 850263,
    "8.4.0": 8490,
    "12.0.5": 91,
    "8.3.1": 4496,
    "12.0.6": 32378,
    "2.1.1": 4,
    "3.1.0": 198,
    "5.0.2": 6,
    "8.2.0": 15,
    "8.2.1": 98,
    "5.0.1": 3,
    "7.0.0": 602,
    "4.1.0": 5,
    "8.0.1": 19,
    "3.0.4": 5,
    "8.3.2": 1909,
    "4.3.1": 4,
    "4.1.2": 216,
    "5.0.3": 703,
    "14.0.0": 655415,
    "3.0.6": 3,
    "8.0.0": 595,
    "4.0.1": 6,
    "5.0.0": 83,
    "13.0.2": 522578,
    "4.3.0": 7882,
    "4.2.0": 4,
    "8.2.2": 244,
    "11.0.1": 94086,
    "12.0.1": 1331,
    "9.0.0": 14,
    "4.0.2": 9,
    "2.1.3": 4,
    "3.0.7": 8,
    "3.0.0": 3,
    "12.3.0": 28996,
    "4.1.1": 4,
    "4.4.0": 56185,
    "2.1.0": 4,
    "6.1.1": 40617,
    "12.0.0": 125,
    "2.2.0": 10,
    "6.0.0": 211,
    "6.1.0": 4,
    "3.0.1": 4,
    "8.4.2": 792415,
    "6.0.4": 242,
    "3.0.3": 3,
    "12.3.2": 4944471,
    "9.1.0": 30080,
    "11.0.0": 51099,
    "5.1.0": 2034,
    "13.0.1": 1090785,
    "2.2.1": 19,
    "3.0.5": 4,
    "8.1.0": 1168,
    "12.0.3": 15942,
    "7.0.1": 11466
  },
  "end": "2024-03-04T04:47:01.703Z",
  "start": "2024-02-26T04:47:01.703Z"
}