{
  "package": "fastify-plugin",
  "downloads": {
    "4.4.0": 152673,
    "4.0.0": 5069,
    "2.3.0": 1378,
    "2.3.2": 731,
    "4.2.1": 35466,
    "4.3.0": 53723,
    "0.2.0": 4,
    "1.0.0": 4,
    "1.6.0": 10900,
    "4.2.0": 7762,
    "1.2.0": 137,
    "4.5.0": 385955,
    "1.1.3": 20,
    "0.1.1": 868,
    "2.3.3": 979,
    "1.1.1": 4,
    "1.5.0": 1688,
    "0.1.0": 5,
    "2.3.1": 221,
    "1.4.0": 52,
    "2.0.3": 2111,
    "3.0.1": 707780,
    "2.0.0": 219,
    "1.0.1": 5,
    "1.3.0": 50,
    "2.0.1": 1861,
    "1.1.0": 4,
    "2.1.1": 68,
    "2.1.0": 355,
    "1.1.2": 4,
    "2.2.0": 134,
    "1.6.1": 59253,
    "3.0.0": 139964,
    "1.2.1": 91,
    "2.3.4": 151727,
    "4.1.0": 6393,
    "4.5.1": 963942,
    "2.0.2": 52,
    "0.2.2": 4484,
    "0.2.1": 10
  },
  "end": "2024-03-04T04:45:12.685Z",
  "start": "2024-02-26T04:45:12.685Z"
}