{
  "package": "@wdio/protocols",
  "downloads": {
    "6.0.12": 3081,
    "8.0.0-alpha.328": 1,
    "7.11.0": 5312,
    "8.24.12": 95444,
    "7.20.0": 4819,
    "8.11.0": 28462,
    "5.15.1": 3252,
    "6.0.0-beta.0": 1,
    "8.24.9": 53,
    "6.1.11": 11024,
    "6.6.0": 23812,
    "7.16.7": 235893,
    "8.8.1": 14958,
    "8.0.0-alpha.331": 1,
    "8.0.0-alpha.507": 1,
    "7.0.0-beta.1": 1,
    "8.1.0": 10744,
    "7.13.0": 2155,
    "5.15.6": 211,
    "7.5.3": 19827,
    "8.14.6": 26088,
    "6.0.0-alpha.1": 1,
    "6.10.6": 29914,
    "7.1.1": 4242,
    "8.0.0-alpha.600": 1,
    "5.15.4": 194,
    "8.0.0-alpha.240": 2,
    "8.3.11": 28760,
    "8.0.0-alpha.621": 1,
    "8.0.0-alpha.213": 1,
    "8.0.0-alpha.518": 2,
    "6.10.0": 7788,
    "7.12.1": 7697,
    "8.20.4": 13969,
    "8.0.0-alpha.505": 1,
    "8.0.0-alpha.547": 7,
    "7.16.1": 7835,
    "7.0.0-beta.0": 405,
    "8.0.0-alpha.243": 1,
    "5.13.2": 494,
    "8.0.0-alpha.330": 1,
    "8.0.15": 248,
    "8.2.0": 13874,
    "6.3.0": 3096,
    "7.20.6": 26543,
    "8.0.0-alpha.239": 1,
    "6.3.6": 17288,
    "8.24.8": 1,
    "6.1.14": 10778,
    "7.20.4": 30714,
    "7.20.8-alpha.504": 6,
    "7.7.4": 12438,
    "7.19.0": 42014,
    "8.0.0-alpha.327": 1,
    "8.0.0-alpha.593": 1,
    "8.0.0-alpha.219": 1,
    "6.0.11": 2,
    "8.0.0-alpha.516": 1,
    "8.29.7": 20055,
    "8.0.0-alpha.537": 1,
    "7.4.2": 3123,
    "6.8.0": 4584,
    "5.16.0": 7164,
    "8.0.0-alpha.577": 13,
    "8.3.5": 11313,
    "5.19.0": 6479,
    "6.0.7": 2,
    "8.0.0-alpha.329": 1,
    "8.0.0-alpha.411": 1,
    "8.18.0": 13775,
    "7.0.0": 10271,
    "8.0.0-alpha.631": 59,
    "8.0.0-alpha.504": 1,
    "7.10.1": 1665,
    "8.10.2": 8093,
    "8.0.0-alpha.563": 1,
    "8.0.0-alpha.512": 1,
    "6.0.8": 214,
    "7.16.0": 305,
    "5.22.1": 290692,
    "8.0.0-alpha.629": 1,
    "8.0.0-alpha.508": 1,
    "6.0.0-beta.1": 52,
    "5.14.0": 3780,
    "8.32.0": 235239,
    "6.0.1": 1144,
    "6.1.25": 8668,
    "5.13.0-alpha.0": 1466,
    "7.13.2": 8079,
    "7.22.0": 125806,
    "6.12.0": 341279,
    "5.16.4": 483,
    "8.0.0": 4325,
    "8.0.0-alpha.598": 2,
    "8.0.0-alpha.249": 1,
    "5.18.7": 3516,
    "8.0.0-alpha.365": 1,
    "8.5.7": 1911,
    "7.4.1": 2,
    "8.0.0-alpha.630": 1,
    "8.0.0-alpha.565": 1,
    "8.0.0-alpha.619": 1,
    "7.20.2": 3668,
    "6.1.2": 1482,
    "8.0.0-alpha.607": 2,
    "8.0.0-alpha.589": 2,
    "6.0.0-alpha.0": 1,
    "8.0.0-alpha.620": 2,
    "8.22.0": 4060,
    "8.6.6": 3343,
    "5.16.7": 19229,
    "8.0.0-alpha.412": 1,
    "8.0.0-alpha.558": 1,
    "7.27.0": 515046,
    "7.12.0": 238,
    "7.17.3": 3892,
    "8.20.3": 555,
    "8.16.5": 22892,
    "8.5.6": 84,
    "8.23.0": 12943
  },
  "end": "2024-03-04T04:45:32.648Z",
  "start": "2024-02-26T04:45:32.648Z"
}