{
  "package": "mochawesome-report-generator",
  "downloads": {
    "3.1.1": 124,
    "4.0.1": 25189,
    "3.1.0": 168,
    "1.1.0": 348,
    "2.0.3": 6,
    "3.1.3": 355,
    "2.0.2": 1,
    "3.1.5": 49596,
    "2.2.0": 1,
    "3.1.2": 2271,
    "4.1.0": 139792,
    "6.0.0": 3825,
    "2.0.1": 1,
    "6.0.1": 125192,
    "5.2.0": 395309,
    "2.1.0": 1,
    "1.0.3": 1,
    "6.1.0": 59737,
    "4.0.0-alpha.2": 372,
    "2.2.2": 124,
    "6.1.1": 17698,
    "2.3.1": 224,
    "2.2.1": 2,
    "6.2.0": 1168242,
    "3.0.1": 4,
    "5.0.0": 1,
    "1.1.2": 99,
    "2.3.2": 12199,
    "3.1.4": 948,
    "4.0.0": 296,
    "5.1.0": 95221
  },
  "end": "2024-03-04T04:45:16.558Z",
  "start": "2024-02-26T04:45:16.558Z"
}