{
  "package": "is-svg",
  "downloads": {
    "4.3.2": 521748,
    "2.0.0": 298,
    "2.0.1": 1701,
    "4.2.0": 1873,
    "0.1.1": 2,
    "0.1.2": 588,
    "1.1.0": 9,
    "2.1.0": 1221207,
    "4.3.0": 15596,
    "1.0.1": 4,
    "1.1.1": 43455,
    "0.1.0": 3,
    "4.4.0": 351576,
    "4.0.0": 14,
    "3.0.0": 3781282,
    "4.2.1": 302154,
    "4.3.1": 207048,
    "5.0.0": 188755,
    "1.0.2": 3,
    "4.2.2": 5412,
    "4.1.0": 87,
    "1.0.0": 2
  },
  "end": "2024-03-04T04:45:23.409Z",
  "start": "2024-02-26T04:45:23.409Z"
}